{"_":[],"open":false,"o":false,"version":false,"v":false,"help":false,"h":false,"quiet":false,"q":false,"silent":false,"s":false,"treeDebug":false,"tree-debug":false,"kernelTracingDebug":false,"kernel-tracing-debug":false,"kernelTracing":false,"kernel-tracing":false,"collectOnly":false,"collect-only":false,"writeTicks":false,"write-ticks":false,"--":["index.js"],"workingDir":"/mnt/d/Software/JS_Expert/modulo12/02-memory-leak/02-memleak-events","argv":["index.js"],"pathToNodeBinary":"/home/katriel_koga/.nvm/versions/node/v16.15.1/bin/node","name":"flamegraph","collectDelay":0,"title":"node index.js","pid":1588,"inlined":{"isEmpty node:internal/fixed_queue":[{"file":"node:internal/fixed_queue","fn":"isEmpty","id":"1","ix":"1","pos":"3637","caller":{"file":"node:internal/process/task_queues","fn":"nextTick","id":"1","ix":"-1","pos":"2602","key":"nextTick node:internal/process/task_queues"}},{"file":"node:internal/fixed_queue","fn":"isEmpty","id":"1","ix":"2","pos":"3084","caller":{"file":"node:internal/process/task_queues","fn":"nextTick","id":"1","ix":"-1","pos":"2602","key":"nextTick node:internal/process/task_queues"}},{"file":"node:internal/fixed_queue","fn":"isEmpty","id":"5","ix":"2","pos":"3637","caller":{"file":"node:internal/process/task_queues","fn":"processTicksAndRejections","id":"5","ix":"-1","pos":"1496","key":"processTicksAndRejections node:internal/process/task_queues"}},{"file":"node:internal/fixed_queue","fn":"isEmpty","id":"5","ix":"3","pos":"3084","caller":{"file":"node:internal/process/task_queues","fn":"processTicksAndRejections","id":"5","ix":"-1","pos":"1496","key":"processTicksAndRejections node:internal/process/task_queues"}},{"file":"node:internal/fixed_queue","fn":"isEmpty","id":"5","ix":"3","pos":"3084","caller":{"file":"node:internal/process/task_queues","fn":"processTicksAndRejections","id":"5","ix":"-1","pos":"1496","key":"processTicksAndRejections node:internal/process/task_queues"}},{"file":"node:internal/fixed_queue","fn":"isEmpty","id":"7","ix":"3","pos":"3637","caller":{"file":"node:internal/streams/readable","fn":"endReadable","id":"7","ix":"-1","pos":"39074","key":"endReadable node:internal/streams/readable"}},{"file":"node:internal/fixed_queue","fn":"isEmpty","id":"7","ix":"4","pos":"3084","caller":{"file":"node:internal/streams/readable","fn":"endReadable","id":"7","ix":"-1","pos":"39074","key":"endReadable node:internal/streams/readable"}},{"file":"node:internal/fixed_queue","fn":"isEmpty","id":"16","ix":"4","pos":"3637","caller":{"file":"node:internal/streams/readable","fn":"Readable.resume","id":"16","ix":"-1","pos":"30769","key":"Readable.resume node:internal/streams/readable"}},{"file":"node:internal/fixed_queue","fn":"isEmpty","id":"16","ix":"5","pos":"3084","caller":{"file":"node:internal/streams/readable","fn":"Readable.resume","id":"16","ix":"-1","pos":"30769","key":"Readable.resume node:internal/streams/readable"}},{"file":"node:internal/fixed_queue","fn":"isEmpty","id":"45","ix":"4","pos":"3637","caller":{"file":"node:_http_server","fn":"resOnFinish","id":"45","ix":"-1","pos":"26108","key":"resOnFinish node:_http_server"}},{"file":"node:internal/fixed_queue","fn":"isEmpty","id":"45","ix":"5","pos":"3084","caller":{"file":"node:_http_server","fn":"resOnFinish","id":"45","ix":"-1","pos":"26108","key":"resOnFinish node:_http_server"}},{"file":"node:internal/fixed_queue","fn":"isEmpty","id":"55","ix":"5","pos":"3637","caller":{"file":"node:net","fn":"Socket.resume","id":"55","ix":"-1","pos":"17240","key":"Socket.resume node:net"}},{"file":"node:internal/fixed_queue","fn":"isEmpty","id":"55","ix":"6","pos":"3084","caller":{"file":"node:net","fn":"Socket.resume","id":"55","ix":"-1","pos":"17240","key":"Socket.resume node:net"}},{"file":"node:internal/fixed_queue","fn":"isEmpty","id":"58","ix":"2","pos":"3637","caller":{"file":"node:internal/streams/writable","fn":"onwrite","id":"58","ix":"-1","pos":"13444","key":"onwrite node:internal/streams/writable"}},{"file":"node:internal/fixed_queue","fn":"isEmpty","id":"58","ix":"3","pos":"3084","caller":{"file":"node:internal/streams/writable","fn":"onwrite","id":"58","ix":"-1","pos":"13444","key":"onwrite node:internal/streams/writable"}},{"file":"node:internal/fixed_queue","fn":"isEmpty","id":"64","ix":"2","pos":"3637","caller":{"file":"node:internal/streams/destroy","fn":"onDestroy","id":"64","ix":"-1","pos":"1535","key":"onDestroy node:internal/streams/destroy"}},{"file":"node:internal/fixed_queue","fn":"isEmpty","id":"64","ix":"3","pos":"3084","caller":{"file":"node:internal/streams/destroy","fn":"onDestroy","id":"64","ix":"-1","pos":"1535","key":"onDestroy node:internal/streams/destroy"}},{"file":"node:internal/fixed_queue","fn":"isEmpty","id":"93","ix":"0","pos":"3084","caller":{"file":"node:internal/fixed_queue","fn":"shift","id":"93","ix":"-1","pos":"3954","key":"shift node:internal/fixed_queue"}},{"file":"node:internal/fixed_queue","fn":"isEmpty","id":"96","ix":"2","pos":"3637","caller":{"file":"node:internal/process/task_queues","fn":"processTicksAndRejections","id":"96","ix":"-1","pos":"1496","key":"processTicksAndRejections node:internal/process/task_queues"}},{"file":"node:internal/fixed_queue","fn":"isEmpty","id":"96","ix":"3","pos":"3084","caller":{"file":"node:internal/process/task_queues","fn":"processTicksAndRejections","id":"96","ix":"-1","pos":"1496","key":"processTicksAndRejections node:internal/process/task_queues"}},{"file":"node:internal/fixed_queue","fn":"isEmpty","id":"96","ix":"3","pos":"3084","caller":{"file":"node:internal/process/task_queues","fn":"processTicksAndRejections","id":"96","ix":"-1","pos":"1496","key":"processTicksAndRejections node:internal/process/task_queues"}},{"file":"node:internal/fixed_queue","fn":"isEmpty","id":"98","ix":"1","pos":"3637","caller":{"file":"node:internal/process/task_queues","fn":"nextTick","id":"98","ix":"-1","pos":"2602","key":"nextTick node:internal/process/task_queues"}},{"file":"node:internal/fixed_queue","fn":"isEmpty","id":"98","ix":"2","pos":"3084","caller":{"file":"node:internal/process/task_queues","fn":"nextTick","id":"98","ix":"-1","pos":"2602","key":"nextTick node:internal/process/task_queues"}}],"newAsyncId node:internal/async_hooks":[{"file":"node:internal/async_hooks","fn":"newAsyncId","id":"1","ix":"3","pos":"14513","caller":{"file":"node:internal/process/task_queues","fn":"nextTick","id":"1","ix":"-1","pos":"2602","key":"nextTick node:internal/process/task_queues"}},{"file":"node:internal/async_hooks","fn":"newAsyncId","id":"7","ix":"5","pos":"14513","caller":{"file":"node:internal/streams/readable","fn":"endReadable","id":"7","ix":"-1","pos":"39074","key":"endReadable node:internal/streams/readable"}},{"file":"node:internal/async_hooks","fn":"newAsyncId","id":"16","ix":"6","pos":"14513","caller":{"file":"node:internal/streams/readable","fn":"Readable.resume","id":"16","ix":"-1","pos":"30769","key":"Readable.resume node:internal/streams/readable"}},{"file":"node:internal/async_hooks","fn":"newAsyncId","id":"28","ix":"0","pos":"14513","caller":{"file":"node:internal/timers","fn":"initAsyncResource","id":"28","ix":"-1","pos":"5425","key":"initAsyncResource node:internal/timers"}},{"file":"node:internal/async_hooks","fn":"newAsyncId","id":"44","ix":"1","pos":"14513","caller":{"file":"node:internal/timers","fn":"Timeout","id":"44","ix":"-1","pos":"5778","key":"Timeout node:internal/timers"}},{"file":"node:internal/async_hooks","fn":"newAsyncId","id":"45","ix":"6","pos":"14513","caller":{"file":"node:_http_server","fn":"resOnFinish","id":"45","ix":"-1","pos":"26108","key":"resOnFinish node:_http_server"}},{"file":"node:internal/async_hooks","fn":"newAsyncId","id":"55","ix":"7","pos":"14513","caller":{"file":"node:net","fn":"Socket.resume","id":"55","ix":"-1","pos":"17240","key":"Socket.resume node:net"}},{"file":"node:internal/async_hooks","fn":"newAsyncId","id":"58","ix":"4","pos":"14513","caller":{"file":"node:internal/streams/writable","fn":"onwrite","id":"58","ix":"-1","pos":"13444","key":"onwrite node:internal/streams/writable"}},{"file":"node:internal/async_hooks","fn":"newAsyncId","id":"64","ix":"4","pos":"14513","caller":{"file":"node:internal/streams/destroy","fn":"onDestroy","id":"64","ix":"-1","pos":"1535","key":"onDestroy node:internal/streams/destroy"}},{"file":"node:internal/async_hooks","fn":"newAsyncId","id":"80","ix":"5","pos":"14513","caller":{"file":"node:timers","fn":"setInterval","id":"80","ix":"-1","pos":"5786","key":"setInterval node:timers"}},{"file":"node:internal/async_hooks","fn":"newAsyncId","id":"98","ix":"3","pos":"14513","caller":{"file":"node:internal/process/task_queues","fn":"nextTick","id":"98","ix":"-1","pos":"2602","key":"nextTick node:internal/process/task_queues"}}],"initHooksExist node:internal/async_hooks":[{"file":"node:internal/async_hooks","fn":"initHooksExist","id":"1","ix":"4","pos":"16193","caller":{"file":"node:internal/process/task_queues","fn":"nextTick","id":"1","ix":"-1","pos":"2602","key":"nextTick node:internal/process/task_queues"}},{"file":"node:internal/async_hooks","fn":"initHooksExist","id":"7","ix":"6","pos":"16193","caller":{"file":"node:internal/streams/readable","fn":"endReadable","id":"7","ix":"-1","pos":"39074","key":"endReadable node:internal/streams/readable"}},{"file":"node:internal/async_hooks","fn":"initHooksExist","id":"16","ix":"7","pos":"16193","caller":{"file":"node:internal/streams/readable","fn":"Readable.resume","id":"16","ix":"-1","pos":"30769","key":"Readable.resume node:internal/streams/readable"}},{"file":"node:internal/async_hooks","fn":"initHooksExist","id":"28","ix":"1","pos":"16193","caller":{"file":"node:internal/timers","fn":"initAsyncResource","id":"28","ix":"-1","pos":"5425","key":"initAsyncResource node:internal/timers"}},{"file":"node:internal/async_hooks","fn":"initHooksExist","id":"44","ix":"2","pos":"16193","caller":{"file":"node:internal/timers","fn":"Timeout","id":"44","ix":"-1","pos":"5778","key":"Timeout node:internal/timers"}},{"file":"node:internal/async_hooks","fn":"initHooksExist","id":"45","ix":"7","pos":"16193","caller":{"file":"node:_http_server","fn":"resOnFinish","id":"45","ix":"-1","pos":"26108","key":"resOnFinish node:_http_server"}},{"file":"node:internal/async_hooks","fn":"initHooksExist","id":"55","ix":"8","pos":"16193","caller":{"file":"node:net","fn":"Socket.resume","id":"55","ix":"-1","pos":"17240","key":"Socket.resume node:net"}},{"file":"node:internal/async_hooks","fn":"initHooksExist","id":"58","ix":"5","pos":"16193","caller":{"file":"node:internal/streams/writable","fn":"onwrite","id":"58","ix":"-1","pos":"13444","key":"onwrite node:internal/streams/writable"}},{"file":"node:internal/async_hooks","fn":"initHooksExist","id":"64","ix":"5","pos":"16193","caller":{"file":"node:internal/streams/destroy","fn":"onDestroy","id":"64","ix":"-1","pos":"1535","key":"onDestroy node:internal/streams/destroy"}},{"file":"node:internal/async_hooks","fn":"initHooksExist","id":"80","ix":"6","pos":"16193","caller":{"file":"node:timers","fn":"setInterval","id":"80","ix":"-1","pos":"5786","key":"setInterval node:timers"}},{"file":"node:internal/async_hooks","fn":"initHooksExist","id":"98","ix":"4","pos":"16193","caller":{"file":"node:internal/process/task_queues","fn":"nextTick","id":"98","ix":"-1","pos":"2602","key":"nextTick node:internal/process/task_queues"}}],"hasHooks node:internal/async_hooks":[{"file":"node:internal/async_hooks","fn":"hasHooks","id":"1","ix":"5","pos":"16061","caller":{"file":"node:internal/process/task_queues","fn":"nextTick","id":"1","ix":"-1","pos":"2602","key":"nextTick node:internal/process/task_queues"}},{"file":"node:internal/async_hooks","fn":"hasHooks","id":"4","ix":"1","pos":"16061","caller":{"file":"node:internal/async_hooks","fn":"popAsyncContext","id":"4","ix":"-1","pos":"18141","key":"popAsyncContext node:internal/async_hooks"}},{"file":"node:internal/async_hooks","fn":"hasHooks","id":"5","ix":"1","pos":"16061","caller":{"file":"node:internal/process/task_queues","fn":"processTicksAndRejections","id":"5","ix":"-1","pos":"1496","key":"processTicksAndRejections node:internal/process/task_queues"}},{"file":"node:internal/async_hooks","fn":"hasHooks","id":"5","ix":"1","pos":"16061","caller":{"file":"node:internal/process/task_queues","fn":"processTicksAndRejections","id":"5","ix":"-1","pos":"1496","key":"processTicksAndRejections node:internal/process/task_queues"}},{"file":"node:internal/async_hooks","fn":"hasHooks","id":"5","ix":"1","pos":"16061","caller":{"file":"node:internal/process/task_queues","fn":"processTicksAndRejections","id":"5","ix":"-1","pos":"1496","key":"processTicksAndRejections node:internal/process/task_queues"}},{"file":"node:internal/async_hooks","fn":"hasHooks","id":"5","ix":"1","pos":"16061","caller":{"file":"node:internal/process/task_queues","fn":"processTicksAndRejections","id":"5","ix":"-1","pos":"1496","key":"processTicksAndRejections node:internal/process/task_queues"}},{"file":"node:internal/async_hooks","fn":"hasHooks","id":"7","ix":"7","pos":"16061","caller":{"file":"node:internal/streams/readable","fn":"endReadable","id":"7","ix":"-1","pos":"39074","key":"endReadable node:internal/streams/readable"}},{"file":"node:internal/async_hooks","fn":"hasHooks","id":"16","ix":"8","pos":"16061","caller":{"file":"node:internal/streams/readable","fn":"Readable.resume","id":"16","ix":"-1","pos":"30769","key":"Readable.resume node:internal/streams/readable"}},{"file":"node:internal/async_hooks","fn":"hasHooks","id":"22","ix":"0","pos":"16061","caller":{"file":"node:internal/async_hooks","fn":"emitAfterScript","id":"22","ix":"-1","pos":"17041","key":"emitAfterScript node:internal/async_hooks"}},{"file":"node:internal/async_hooks","fn":"hasHooks","id":"22","ix":"0","pos":"16061","caller":{"file":"node:internal/async_hooks","fn":"emitAfterScript","id":"22","ix":"-1","pos":"17041","key":"emitAfterScript node:internal/async_hooks"}},{"file":"node:internal/async_hooks","fn":"hasHooks","id":"28","ix":"2","pos":"16061","caller":{"file":"node:internal/timers","fn":"initAsyncResource","id":"28","ix":"-1","pos":"5425","key":"initAsyncResource node:internal/timers"}},{"file":"node:internal/async_hooks","fn":"hasHooks","id":"44","ix":"3","pos":"16061","caller":{"file":"node:internal/timers","fn":"Timeout","id":"44","ix":"-1","pos":"5778","key":"Timeout node:internal/timers"}},{"file":"node:internal/async_hooks","fn":"hasHooks","id":"45","ix":"8","pos":"16061","caller":{"file":"node:_http_server","fn":"resOnFinish","id":"45","ix":"-1","pos":"26108","key":"resOnFinish node:_http_server"}},{"file":"node:internal/async_hooks","fn":"hasHooks","id":"49","ix":"3","pos":"16061","caller":{"file":"node:internal/timers","fn":"listOnTimeout","id":"49","ix":"-1","pos":"14905","key":"listOnTimeout node:internal/timers"}},{"file":"node:internal/async_hooks","fn":"hasHooks","id":"49","ix":"3","pos":"16061","caller":{"file":"node:internal/timers","fn":"listOnTimeout","id":"49","ix":"-1","pos":"14905","key":"listOnTimeout node:internal/timers"}},{"file":"node:internal/async_hooks","fn":"hasHooks","id":"49","ix":"3","pos":"16061","caller":{"file":"node:internal/timers","fn":"listOnTimeout","id":"49","ix":"-1","pos":"14905","key":"listOnTimeout node:internal/timers"}},{"file":"node:internal/async_hooks","fn":"hasHooks","id":"52","ix":"0","pos":"16061","caller":{"file":"node:internal/async_hooks","fn":"emitBeforeScript","id":"52","ix":"-1","pos":"16863","key":"emitBeforeScript node:internal/async_hooks"}},{"file":"node:internal/async_hooks","fn":"hasHooks","id":"55","ix":"9","pos":"16061","caller":{"file":"node:net","fn":"Socket.resume","id":"55","ix":"-1","pos":"17240","key":"Socket.resume node:net"}},{"file":"node:internal/async_hooks","fn":"hasHooks","id":"58","ix":"6","pos":"16061","caller":{"file":"node:internal/streams/writable","fn":"onwrite","id":"58","ix":"-1","pos":"13444","key":"onwrite node:internal/streams/writable"}},{"file":"node:internal/async_hooks","fn":"hasHooks","id":"64","ix":"6","pos":"16061","caller":{"file":"node:internal/streams/destroy","fn":"onDestroy","id":"64","ix":"-1","pos":"1535","key":"onDestroy node:internal/streams/destroy"}},{"file":"node:internal/async_hooks","fn":"hasHooks","id":"69","ix":"3","pos":"16061","caller":{"file":"node:internal/timers","fn":"listOnTimeout","id":"69","ix":"-1","pos":"14905","key":"listOnTimeout node:internal/timers"}},{"file":"node:internal/async_hooks","fn":"hasHooks","id":"69","ix":"3","pos":"16061","caller":{"file":"node:internal/timers","fn":"listOnTimeout","id":"69","ix":"-1","pos":"14905","key":"listOnTimeout node:internal/timers"}},{"file":"node:internal/async_hooks","fn":"hasHooks","id":"69","ix":"3","pos":"16061","caller":{"file":"node:internal/timers","fn":"listOnTimeout","id":"69","ix":"-1","pos":"14905","key":"listOnTimeout node:internal/timers"}},{"file":"node:internal/async_hooks","fn":"hasHooks","id":"69","ix":"3","pos":"16061","caller":{"file":"node:internal/timers","fn":"listOnTimeout","id":"69","ix":"-1","pos":"14905","key":"listOnTimeout node:internal/timers"}},{"file":"node:internal/async_hooks","fn":"hasHooks","id":"80","ix":"7","pos":"16061","caller":{"file":"node:timers","fn":"setInterval","id":"80","ix":"-1","pos":"5786","key":"setInterval node:timers"}},{"file":"node:internal/async_hooks","fn":"hasHooks","id":"83","ix":"9","pos":"16061","caller":{"file":"node:internal/stream_base_commons","fn":"setStreamTimeout","id":"83","ix":"-1","pos":"6046","key":"setStreamTimeout node:internal/stream_base_commons"}},{"file":"node:internal/async_hooks","fn":"hasHooks","id":"96","ix":"1","pos":"16061","caller":{"file":"node:internal/process/task_queues","fn":"processTicksAndRejections","id":"96","ix":"-1","pos":"1496","key":"processTicksAndRejections node:internal/process/task_queues"}},{"file":"node:internal/async_hooks","fn":"hasHooks","id":"96","ix":"1","pos":"16061","caller":{"file":"node:internal/process/task_queues","fn":"processTicksAndRejections","id":"96","ix":"-1","pos":"1496","key":"processTicksAndRejections node:internal/process/task_queues"}},{"file":"node:internal/async_hooks","fn":"hasHooks","id":"96","ix":"1","pos":"16061","caller":{"file":"node:internal/process/task_queues","fn":"processTicksAndRejections","id":"96","ix":"-1","pos":"1496","key":"processTicksAndRejections node:internal/process/task_queues"}},{"file":"node:internal/async_hooks","fn":"hasHooks","id":"96","ix":"1","pos":"16061","caller":{"file":"node:internal/process/task_queues","fn":"processTicksAndRejections","id":"96","ix":"-1","pos":"1496","key":"processTicksAndRejections node:internal/process/task_queues"}},{"file":"node:internal/async_hooks","fn":"hasHooks","id":"98","ix":"5","pos":"16061","caller":{"file":"node:internal/process/task_queues","fn":"nextTick","id":"98","ix":"-1","pos":"2602","key":"nextTick node:internal/process/task_queues"}}],"push node:internal/fixed_queue":[{"file":"node:internal/fixed_queue","fn":"push","id":"1","ix":"6","pos":"3685","caller":{"file":"node:internal/process/task_queues","fn":"nextTick","id":"1","ix":"-1","pos":"2602","key":"nextTick node:internal/process/task_queues"}},{"file":"node:internal/fixed_queue","fn":"push","id":"1","ix":"9","pos":"3208","caller":{"file":"node:internal/process/task_queues","fn":"nextTick","id":"1","ix":"-1","pos":"2602","key":"nextTick node:internal/process/task_queues"}},{"file":"node:internal/fixed_queue","fn":"push","id":"7","ix":"8","pos":"3685","caller":{"file":"node:internal/streams/readable","fn":"endReadable","id":"7","ix":"-1","pos":"39074","key":"endReadable node:internal/streams/readable"}},{"file":"node:internal/fixed_queue","fn":"push","id":"7","ix":"11","pos":"3208","caller":{"file":"node:internal/streams/readable","fn":"endReadable","id":"7","ix":"-1","pos":"39074","key":"endReadable node:internal/streams/readable"}},{"file":"node:internal/fixed_queue","fn":"push","id":"16","ix":"9","pos":"3685","caller":{"file":"node:internal/streams/readable","fn":"Readable.resume","id":"16","ix":"-1","pos":"30769","key":"Readable.resume node:internal/streams/readable"}},{"file":"node:internal/fixed_queue","fn":"push","id":"16","ix":"12","pos":"3208","caller":{"file":"node:internal/streams/readable","fn":"Readable.resume","id":"16","ix":"-1","pos":"30769","key":"Readable.resume node:internal/streams/readable"}},{"file":"node:internal/fixed_queue","fn":"push","id":"45","ix":"14","pos":"3685","caller":{"file":"node:_http_server","fn":"resOnFinish","id":"45","ix":"-1","pos":"26108","key":"resOnFinish node:_http_server"}},{"file":"node:internal/fixed_queue","fn":"push","id":"45","ix":"17","pos":"3208","caller":{"file":"node:_http_server","fn":"resOnFinish","id":"45","ix":"-1","pos":"26108","key":"resOnFinish node:_http_server"}},{"file":"node:internal/fixed_queue","fn":"push","id":"55","ix":"10","pos":"3685","caller":{"file":"node:net","fn":"Socket.resume","id":"55","ix":"-1","pos":"17240","key":"Socket.resume node:net"}},{"file":"node:internal/fixed_queue","fn":"push","id":"55","ix":"13","pos":"3208","caller":{"file":"node:net","fn":"Socket.resume","id":"55","ix":"-1","pos":"17240","key":"Socket.resume node:net"}},{"file":"node:internal/fixed_queue","fn":"push","id":"58","ix":"7","pos":"3685","caller":{"file":"node:internal/streams/writable","fn":"onwrite","id":"58","ix":"-1","pos":"13444","key":"onwrite node:internal/streams/writable"}},{"file":"node:internal/fixed_queue","fn":"push","id":"58","ix":"10","pos":"3208","caller":{"file":"node:internal/streams/writable","fn":"onwrite","id":"58","ix":"-1","pos":"13444","key":"onwrite node:internal/streams/writable"}},{"file":"node:internal/fixed_queue","fn":"push","id":"64","ix":"8","pos":"3685","caller":{"file":"node:internal/streams/destroy","fn":"onDestroy","id":"64","ix":"-1","pos":"1535","key":"onDestroy node:internal/streams/destroy"}},{"file":"node:internal/fixed_queue","fn":"push","id":"64","ix":"11","pos":"3208","caller":{"file":"node:internal/streams/destroy","fn":"onDestroy","id":"64","ix":"-1","pos":"1535","key":"onDestroy node:internal/streams/destroy"}},{"file":"node:internal/fixed_queue","fn":"push","id":"97","ix":"1","pos":"3208","caller":{"file":"node:internal/fixed_queue","fn":"push","id":"97","ix":"-1","pos":"3685","key":"push node:internal/fixed_queue"}},{"file":"node:internal/fixed_queue","fn":"push","id":"98","ix":"6","pos":"3685","caller":{"file":"node:internal/process/task_queues","fn":"nextTick","id":"98","ix":"-1","pos":"2602","key":"nextTick node:internal/process/task_queues"}},{"file":"node:internal/fixed_queue","fn":"push","id":"98","ix":"9","pos":"3208","caller":{"file":"node:internal/process/task_queues","fn":"nextTick","id":"98","ix":"-1","pos":"2602","key":"nextTick node:internal/process/task_queues"}}],"isFull node:internal/fixed_queue":[{"file":"node:internal/fixed_queue","fn":"isFull","id":"1","ix":"7","pos":"3139","caller":{"file":"node:internal/process/task_queues","fn":"nextTick","id":"1","ix":"-1","pos":"2602","key":"nextTick node:internal/process/task_queues"}},{"file":"node:internal/fixed_queue","fn":"isFull","id":"7","ix":"9","pos":"3139","caller":{"file":"node:internal/streams/readable","fn":"endReadable","id":"7","ix":"-1","pos":"39074","key":"endReadable node:internal/streams/readable"}},{"file":"node:internal/fixed_queue","fn":"isFull","id":"16","ix":"10","pos":"3139","caller":{"file":"node:internal/streams/readable","fn":"Readable.resume","id":"16","ix":"-1","pos":"30769","key":"Readable.resume node:internal/streams/readable"}},{"file":"node:internal/fixed_queue","fn":"isFull","id":"45","ix":"15","pos":"3139","caller":{"file":"node:_http_server","fn":"resOnFinish","id":"45","ix":"-1","pos":"26108","key":"resOnFinish node:_http_server"}},{"file":"node:internal/fixed_queue","fn":"isFull","id":"55","ix":"11","pos":"3139","caller":{"file":"node:net","fn":"Socket.resume","id":"55","ix":"-1","pos":"17240","key":"Socket.resume node:net"}},{"file":"node:internal/fixed_queue","fn":"isFull","id":"58","ix":"8","pos":"3139","caller":{"file":"node:internal/streams/writable","fn":"onwrite","id":"58","ix":"-1","pos":"13444","key":"onwrite node:internal/streams/writable"}},{"file":"node:internal/fixed_queue","fn":"isFull","id":"64","ix":"9","pos":"3139","caller":{"file":"node:internal/streams/destroy","fn":"onDestroy","id":"64","ix":"-1","pos":"1535","key":"onDestroy node:internal/streams/destroy"}},{"file":"node:internal/fixed_queue","fn":"isFull","id":"97","ix":"0","pos":"3139","caller":{"file":"node:internal/fixed_queue","fn":"push","id":"97","ix":"-1","pos":"3685","key":"push node:internal/fixed_queue"}},{"file":"node:internal/fixed_queue","fn":"isFull","id":"98","ix":"7","pos":"3139","caller":{"file":"node:internal/process/task_queues","fn":"nextTick","id":"98","ix":"-1","pos":"2602","key":"nextTick node:internal/process/task_queues"}}],"getDefaultTriggerAsyncId node:internal/async_hooks":[{"file":"node:internal/async_hooks","fn":"getDefaultTriggerAsyncId","id":"1","ix":"8","pos":"14972","caller":{"file":"node:internal/process/task_queues","fn":"nextTick","id":"1","ix":"-1","pos":"2602","key":"nextTick node:internal/process/task_queues"}},{"file":"node:internal/async_hooks","fn":"getDefaultTriggerAsyncId","id":"7","ix":"10","pos":"14972","caller":{"file":"node:internal/streams/readable","fn":"endReadable","id":"7","ix":"-1","pos":"39074","key":"endReadable node:internal/streams/readable"}},{"file":"node:internal/async_hooks","fn":"getDefaultTriggerAsyncId","id":"16","ix":"11","pos":"14972","caller":{"file":"node:internal/streams/readable","fn":"Readable.resume","id":"16","ix":"-1","pos":"30769","key":"Readable.resume node:internal/streams/readable"}},{"file":"node:internal/async_hooks","fn":"getDefaultTriggerAsyncId","id":"28","ix":"3","pos":"14972","caller":{"file":"node:internal/timers","fn":"initAsyncResource","id":"28","ix":"-1","pos":"5425","key":"initAsyncResource node:internal/timers"}},{"file":"node:internal/async_hooks","fn":"getDefaultTriggerAsyncId","id":"44","ix":"4","pos":"14972","caller":{"file":"node:internal/timers","fn":"Timeout","id":"44","ix":"-1","pos":"5778","key":"Timeout node:internal/timers"}},{"file":"node:internal/async_hooks","fn":"getDefaultTriggerAsyncId","id":"45","ix":"16","pos":"14972","caller":{"file":"node:_http_server","fn":"resOnFinish","id":"45","ix":"-1","pos":"26108","key":"resOnFinish node:_http_server"}},{"file":"node:internal/async_hooks","fn":"getDefaultTriggerAsyncId","id":"55","ix":"12","pos":"14972","caller":{"file":"node:net","fn":"Socket.resume","id":"55","ix":"-1","pos":"17240","key":"Socket.resume node:net"}},{"file":"node:internal/async_hooks","fn":"getDefaultTriggerAsyncId","id":"58","ix":"9","pos":"14972","caller":{"file":"node:internal/streams/writable","fn":"onwrite","id":"58","ix":"-1","pos":"13444","key":"onwrite node:internal/streams/writable"}},{"file":"node:internal/async_hooks","fn":"getDefaultTriggerAsyncId","id":"64","ix":"10","pos":"14972","caller":{"file":"node:internal/streams/destroy","fn":"onDestroy","id":"64","ix":"-1","pos":"1535","key":"onDestroy node:internal/streams/destroy"}},{"file":"node:internal/async_hooks","fn":"getDefaultTriggerAsyncId","id":"80","ix":"8","pos":"14972","caller":{"file":"node:timers","fn":"setInterval","id":"80","ix":"-1","pos":"5786","key":"setInterval node:timers"}},{"file":"node:internal/async_hooks","fn":"getDefaultTriggerAsyncId","id":"98","ix":"8","pos":"14972","caller":{"file":"node:internal/process/task_queues","fn":"nextTick","id":"98","ix":"-1","pos":"2602","key":"nextTick node:internal/process/task_queues"}}],"enabledHooksExist node:internal/async_hooks":[{"file":"node:internal/async_hooks","fn":"enabledHooksExist","id":"4","ix":"0","pos":"16135","caller":{"file":"node:internal/async_hooks","fn":"popAsyncContext","id":"4","ix":"-1","pos":"18141","key":"popAsyncContext node:internal/async_hooks"}},{"file":"node:internal/async_hooks","fn":"enabledHooksExist","id":"5","ix":"12","pos":"16135","caller":{"file":"node:internal/process/task_queues","fn":"processTicksAndRejections","id":"5","ix":"-1","pos":"1496","key":"processTicksAndRejections node:internal/process/task_queues"}},{"file":"node:internal/async_hooks","fn":"enabledHooksExist","id":"22","ix":"2","pos":"16135","caller":{"file":"node:internal/async_hooks","fn":"emitAfterScript","id":"22","ix":"-1","pos":"17041","key":"emitAfterScript node:internal/async_hooks"}},{"file":"node:internal/async_hooks","fn":"enabledHooksExist","id":"49","ix":"11","pos":"16135","caller":{"file":"node:internal/timers","fn":"listOnTimeout","id":"49","ix":"-1","pos":"14905","key":"listOnTimeout node:internal/timers"}},{"file":"node:internal/async_hooks","fn":"enabledHooksExist","id":"69","ix":"11","pos":"16135","caller":{"file":"node:internal/timers","fn":"listOnTimeout","id":"69","ix":"-1","pos":"14905","key":"listOnTimeout node:internal/timers"}},{"file":"node:internal/async_hooks","fn":"enabledHooksExist","id":"96","ix":"10","pos":"16135","caller":{"file":"node:internal/process/task_queues","fn":"processTicksAndRejections","id":"96","ix":"-1","pos":"1496","key":"processTicksAndRejections node:internal/process/task_queues"}}],"destroyHooksExist node:internal/async_hooks":[{"file":"node:internal/async_hooks","fn":"destroyHooksExist","id":"5","ix":"0","pos":"16312","caller":{"file":"node:internal/process/task_queues","fn":"processTicksAndRejections","id":"5","ix":"-1","pos":"1496","key":"processTicksAndRejections node:internal/process/task_queues"}},{"file":"node:internal/async_hooks","fn":"destroyHooksExist","id":"69","ix":"2","pos":"16312","caller":{"file":"node:internal/timers","fn":"listOnTimeout","id":"69","ix":"-1","pos":"14905","key":"listOnTimeout node:internal/timers"}},{"file":"node:internal/async_hooks","fn":"destroyHooksExist","id":"83","ix":"8","pos":"16312","caller":{"file":"node:internal/stream_base_commons","fn":"setStreamTimeout","id":"83","ix":"-1","pos":"6046","key":"setStreamTimeout node:internal/stream_base_commons"}},{"file":"node:internal/async_hooks","fn":"destroyHooksExist","id":"96","ix":"0","pos":"16312","caller":{"file":"node:internal/process/task_queues","fn":"processTicksAndRejections","id":"96","ix":"-1","pos":"1496","key":"processTicksAndRejections node:internal/process/task_queues"}}],"setHasTickScheduled node:internal/process/task_queues":[{"file":"node:internal/process/task_queues","fn":"setHasTickScheduled","id":"5","ix":"4","pos":"1104","caller":{"file":"node:internal/process/task_queues","fn":"processTicksAndRejections","id":"5","ix":"-1","pos":"1496","key":"processTicksAndRejections node:internal/process/task_queues"}},{"file":"node:internal/process/task_queues","fn":"setHasTickScheduled","id":"96","ix":"4","pos":"1104","caller":{"file":"node:internal/process/task_queues","fn":"processTicksAndRejections","id":"96","ix":"-1","pos":"1496","key":"processTicksAndRejections node:internal/process/task_queues"}}],"setHasRejectionToWarn node:internal/process/promises":[{"file":"node:internal/process/promises","fn":"setHasRejectionToWarn","id":"5","ix":"5","pos":"2095","caller":{"file":"node:internal/process/task_queues","fn":"processTicksAndRejections","id":"5","ix":"-1","pos":"1496","key":"processTicksAndRejections node:internal/process/task_queues"}},{"file":"node:internal/process/promises","fn":"setHasRejectionToWarn","id":"96","ix":"5","pos":"2095","caller":{"file":"node:internal/process/task_queues","fn":"processTicksAndRejections","id":"96","ix":"-1","pos":"1496","key":"processTicksAndRejections node:internal/process/task_queues"}}],"shift node:internal/fixed_queue":[{"file":"node:internal/fixed_queue","fn":"shift","id":"5","ix":"6","pos":"3954","caller":{"file":"node:internal/process/task_queues","fn":"processTicksAndRejections","id":"5","ix":"-1","pos":"1496","key":"processTicksAndRejections node:internal/process/task_queues"}},{"file":"node:internal/fixed_queue","fn":"shift","id":"5","ix":"7","pos":"3300","caller":{"file":"node:internal/process/task_queues","fn":"processTicksAndRejections","id":"5","ix":"-1","pos":"1496","key":"processTicksAndRejections node:internal/process/task_queues"}},{"file":"node:internal/fixed_queue","fn":"shift","id":"93","ix":"1","pos":"3300","caller":{"file":"node:internal/fixed_queue","fn":"shift","id":"93","ix":"-1","pos":"3954","key":"shift node:internal/fixed_queue"}},{"file":"node:internal/fixed_queue","fn":"shift","id":"96","ix":"6","pos":"3954","caller":{"file":"node:internal/process/task_queues","fn":"processTicksAndRejections","id":"96","ix":"-1","pos":"1496","key":"processTicksAndRejections node:internal/process/task_queues"}},{"file":"node:internal/fixed_queue","fn":"shift","id":"96","ix":"7","pos":"3300","caller":{"file":"node:internal/process/task_queues","fn":"processTicksAndRejections","id":"96","ix":"-1","pos":"1496","key":"processTicksAndRejections node:internal/process/task_queues"}}],"emitAfterScript node:internal/async_hooks":[{"file":"node:internal/async_hooks","fn":"emitAfterScript","id":"5","ix":"8","pos":"17041","caller":{"file":"node:internal/process/task_queues","fn":"processTicksAndRejections","id":"5","ix":"-1","pos":"1496","key":"processTicksAndRejections node:internal/process/task_queues"}},{"file":"node:internal/async_hooks","fn":"emitAfterScript","id":"49","ix":"2","pos":"17041","caller":{"file":"node:internal/timers","fn":"listOnTimeout","id":"49","ix":"-1","pos":"14905","key":"listOnTimeout node:internal/timers"}},{"file":"node:internal/async_hooks","fn":"emitAfterScript","id":"69","ix":"4","pos":"17041","caller":{"file":"node:internal/timers","fn":"listOnTimeout","id":"69","ix":"-1","pos":"14905","key":"listOnTimeout node:internal/timers"}},{"file":"node:internal/async_hooks","fn":"emitAfterScript","id":"96","ix":"8","pos":"17041","caller":{"file":"node:internal/process/task_queues","fn":"processTicksAndRejections","id":"96","ix":"-1","pos":"1496","key":"processTicksAndRejections node:internal/process/task_queues"}}],"emitBeforeScript node:internal/async_hooks":[{"file":"node:internal/async_hooks","fn":"emitBeforeScript","id":"5","ix":"9","pos":"16863","caller":{"file":"node:internal/process/task_queues","fn":"processTicksAndRejections","id":"5","ix":"-1","pos":"1496","key":"processTicksAndRejections node:internal/process/task_queues"}},{"file":"node:internal/async_hooks","fn":"emitBeforeScript","id":"49","ix":"6","pos":"16863","caller":{"file":"node:internal/timers","fn":"listOnTimeout","id":"49","ix":"-1","pos":"14905","key":"listOnTimeout node:internal/timers"}},{"file":"node:internal/async_hooks","fn":"emitBeforeScript","id":"69","ix":"5","pos":"16863","caller":{"file":"node:internal/timers","fn":"listOnTimeout","id":"69","ix":"-1","pos":"14905","key":"listOnTimeout node:internal/timers"}},{"file":"node:internal/async_hooks","fn":"emitBeforeScript","id":"96","ix":"11","pos":"16863","caller":{"file":"node:internal/process/task_queues","fn":"processTicksAndRejections","id":"96","ix":"-1","pos":"1496","key":"processTicksAndRejections node:internal/process/task_queues"}}],"pushAsyncContext node:internal/async_hooks":[{"file":"node:internal/async_hooks","fn":"pushAsyncContext","id":"5","ix":"10","pos":"17507","caller":{"file":"node:internal/process/task_queues","fn":"processTicksAndRejections","id":"5","ix":"-1","pos":"1496","key":"processTicksAndRejections node:internal/process/task_queues"}},{"file":"node:internal/async_hooks","fn":"pushAsyncContext","id":"49","ix":"9","pos":"17507","caller":{"file":"node:internal/timers","fn":"listOnTimeout","id":"49","ix":"-1","pos":"14905","key":"listOnTimeout node:internal/timers"}},{"file":"node:internal/async_hooks","fn":"pushAsyncContext","id":"52","ix":"1","pos":"17507","caller":{"file":"node:internal/async_hooks","fn":"emitBeforeScript","id":"52","ix":"-1","pos":"16863","key":"emitBeforeScript node:internal/async_hooks"}},{"file":"node:internal/async_hooks","fn":"pushAsyncContext","id":"69","ix":"9","pos":"17507","caller":{"file":"node:internal/timers","fn":"listOnTimeout","id":"69","ix":"-1","pos":"14905","key":"listOnTimeout node:internal/timers"}},{"file":"node:internal/async_hooks","fn":"pushAsyncContext","id":"96","ix":"12","pos":"17507","caller":{"file":"node:internal/process/task_queues","fn":"processTicksAndRejections","id":"96","ix":"-1","pos":"1496","key":"processTicksAndRejections node:internal/process/task_queues"}}],"popAsyncContext node:internal/async_hooks":[{"file":"node:internal/async_hooks","fn":"popAsyncContext","id":"5","ix":"11","pos":"18141","caller":{"file":"node:internal/process/task_queues","fn":"processTicksAndRejections","id":"5","ix":"-1","pos":"1496","key":"processTicksAndRejections node:internal/process/task_queues"}},{"file":"node:internal/async_hooks","fn":"popAsyncContext","id":"22","ix":"1","pos":"18141","caller":{"file":"node:internal/async_hooks","fn":"emitAfterScript","id":"22","ix":"-1","pos":"17041","key":"emitAfterScript node:internal/async_hooks"}},{"file":"node:internal/async_hooks","fn":"popAsyncContext","id":"49","ix":"10","pos":"18141","caller":{"file":"node:internal/timers","fn":"listOnTimeout","id":"49","ix":"-1","pos":"14905","key":"listOnTimeout node:internal/timers"}},{"file":"node:internal/async_hooks","fn":"popAsyncContext","id":"69","ix":"10","pos":"18141","caller":{"file":"node:internal/timers","fn":"listOnTimeout","id":"69","ix":"-1","pos":"14905","key":"listOnTimeout node:internal/timers"}},{"file":"node:internal/async_hooks","fn":"popAsyncContext","id":"96","ix":"9","pos":"18141","caller":{"file":"node:internal/process/task_queues","fn":"processTicksAndRejections","id":"96","ix":"-1","pos":"1496","key":"processTicksAndRejections node:internal/process/task_queues"}}],"noop node:internal/util/debuglog":[{"file":"node:internal/util/debuglog","fn":"noop","id":"7","ix":"0","pos":"1419","caller":{"file":"node:internal/streams/readable","fn":"endReadable","id":"7","ix":"-1","pos":"39074","key":"endReadable node:internal/streams/readable"}},{"file":"node:internal/util/debuglog","fn":"noop","id":"9","ix":"0","pos":"1419","caller":{"file":"node:internal/streams/readable","fn":"Readable.read","id":"9","ix":"-1","pos":"12692","key":"Readable.read node:internal/streams/readable"}},{"file":"node:internal/util/debuglog","fn":"noop","id":"16","ix":"0","pos":"1419","caller":{"file":"node:internal/streams/readable","fn":"Readable.resume","id":"16","ix":"-1","pos":"30769","key":"Readable.resume node:internal/streams/readable"}},{"file":"node:internal/util/debuglog","fn":"noop","id":"17","ix":"0","pos":"1419","caller":{"file":"node:internal/streams/readable","fn":"flow","id":"17","ix":"-1","pos":"31804","key":"flow node:internal/streams/readable"}},{"file":"node:internal/util/debuglog","fn":"noop","id":"25","ix":"0","pos":"1419","caller":{"file":"node:internal/streams/readable","fn":"endReadableNT","id":"25","ix":"-1","pos":"39299","key":"endReadableNT node:internal/streams/readable"}},{"file":"node:internal/util/debuglog","fn":"noop","id":"33","ix":"0","pos":"1419","caller":{"file":"node:_http_common","fn":"parserOnHeadersComplete","id":"33","ix":"-1","pos":"2931","key":"parserOnHeadersComplete node:_http_common"}},{"file":"node:internal/util/debuglog","fn":"noop","id":"40","ix":"1","pos":"1419","caller":{"file":"node:_http_outgoing","fn":"write_","id":"40","ix":"-1","pos":"21766","key":"write_ node:_http_outgoing"}},{"file":"node:internal/util/debuglog","fn":"noop","id":"49","ix":"0","pos":"1419","caller":{"file":"node:internal/timers","fn":"listOnTimeout","id":"49","ix":"-1","pos":"14905","key":"listOnTimeout node:internal/timers"}},{"file":"node:internal/util/debuglog","fn":"noop","id":"49","ix":"0","pos":"1419","caller":{"file":"node:internal/timers","fn":"listOnTimeout","id":"49","ix":"-1","pos":"14905","key":"listOnTimeout node:internal/timers"}},{"file":"node:internal/util/debuglog","fn":"noop","id":"53","ix":"2","pos":"1419","caller":{"file":"node:_http_outgoing","fn":"end","id":"53","ix":"-1","pos":"24416","key":"end node:_http_outgoing"}},{"file":"node:internal/util/debuglog","fn":"noop","id":"55","ix":"1","pos":"1419","caller":{"file":"node:net","fn":"Socket.resume","id":"55","ix":"-1","pos":"17240","key":"Socket.resume node:net"}},{"file":"node:internal/util/debuglog","fn":"noop","id":"62","ix":"0","pos":"1419","caller":{"file":"node:internal/streams/readable","fn":"emitReadable_","id":"62","ix":"-1","pos":"18430","key":"emitReadable_ node:internal/streams/readable"}},{"file":"node:internal/util/debuglog","fn":"noop","id":"62","ix":"0","pos":"1419","caller":{"file":"node:internal/streams/readable","fn":"emitReadable_","id":"62","ix":"-1","pos":"18430","key":"emitReadable_ node:internal/streams/readable"}},{"file":"node:internal/util/debuglog","fn":"noop","id":"65","ix":"0","pos":"1419","caller":{"file":"node:internal/streams/readable","fn":"readableAddChunk","id":"65","ix":"-1","pos":"7908","key":"readableAddChunk node:internal/streams/readable"}},{"file":"node:internal/util/debuglog","fn":"noop","id":"65","ix":"0","pos":"1419","caller":{"file":"node:internal/streams/readable","fn":"readableAddChunk","id":"65","ix":"-1","pos":"7908","key":"readableAddChunk node:internal/streams/readable"}},{"file":"node:internal/util/debuglog","fn":"noop","id":"65","ix":"0","pos":"1419","caller":{"file":"node:internal/streams/readable","fn":"readableAddChunk","id":"65","ix":"-1","pos":"7908","key":"readableAddChunk node:internal/streams/readable"}},{"file":"node:internal/util/debuglog","fn":"noop","id":"65","ix":"0","pos":"1419","caller":{"file":"node:internal/streams/readable","fn":"readableAddChunk","id":"65","ix":"-1","pos":"7908","key":"readableAddChunk node:internal/streams/readable"}},{"file":"node:internal/util/debuglog","fn":"noop","id":"68","ix":"0","pos":"1419","caller":{"file":"node:internal/streams/readable","fn":"resume_","id":"68","ix":"-1","pos":"31257","key":"resume_ node:internal/streams/readable"}},{"file":"node:internal/util/debuglog","fn":"noop","id":"68","ix":"0","pos":"1419","caller":{"file":"node:internal/streams/readable","fn":"resume_","id":"68","ix":"-1","pos":"31257","key":"resume_ node:internal/streams/readable"}},{"file":"node:internal/util/debuglog","fn":"noop","id":"69","ix":"0","pos":"1419","caller":{"file":"node:internal/timers","fn":"listOnTimeout","id":"69","ix":"-1","pos":"14905","key":"listOnTimeout node:internal/timers"}},{"file":"node:internal/util/debuglog","fn":"noop","id":"69","ix":"0","pos":"1419","caller":{"file":"node:internal/timers","fn":"listOnTimeout","id":"69","ix":"-1","pos":"14905","key":"listOnTimeout node:internal/timers"}},{"file":"node:internal/util/debuglog","fn":"noop","id":"69","ix":"0","pos":"1419","caller":{"file":"node:internal/timers","fn":"listOnTimeout","id":"69","ix":"-1","pos":"14905","key":"listOnTimeout node:internal/timers"}},{"file":"node:internal/util/debuglog","fn":"noop","id":"69","ix":"0","pos":"1419","caller":{"file":"node:internal/timers","fn":"listOnTimeout","id":"69","ix":"-1","pos":"14905","key":"listOnTimeout node:internal/timers"}},{"file":"node:internal/util/debuglog","fn":"noop","id":"84","ix":"0","pos":"1419","caller":{"file":"node:_http_server","fn":"onParserExecute","id":"84","ix":"-1","pos":"21546","key":"onParserExecute node:_http_server"}}],"nextTick node:internal/process/task_queues":[{"file":"node:internal/process/task_queues","fn":"nextTick","id":"7","ix":"1","pos":"2602","caller":{"file":"node:internal/streams/readable","fn":"endReadable","id":"7","ix":"-1","pos":"39074","key":"endReadable node:internal/streams/readable"}},{"file":"node:internal/process/task_queues","fn":"nextTick","id":"16","ix":"2","pos":"2602","caller":{"file":"node:internal/streams/readable","fn":"Readable.resume","id":"16","ix":"-1","pos":"30769","key":"Readable.resume node:internal/streams/readable"}},{"file":"node:internal/process/task_queues","fn":"nextTick","id":"45","ix":"2","pos":"2602","caller":{"file":"node:_http_server","fn":"resOnFinish","id":"45","ix":"-1","pos":"26108","key":"resOnFinish node:_http_server"}},{"file":"node:internal/process/task_queues","fn":"nextTick","id":"55","ix":"3","pos":"2602","caller":{"file":"node:net","fn":"Socket.resume","id":"55","ix":"-1","pos":"17240","key":"Socket.resume node:net"}},{"file":"node:internal/process/task_queues","fn":"nextTick","id":"58","ix":"0","pos":"2602","caller":{"file":"node:internal/streams/writable","fn":"onwrite","id":"58","ix":"-1","pos":"13444","key":"onwrite node:internal/streams/writable"}},{"file":"node:internal/process/task_queues","fn":"nextTick","id":"64","ix":"0","pos":"2602","caller":{"file":"node:internal/streams/destroy","fn":"onDestroy","id":"64","ix":"-1","pos":"1535","key":"onDestroy node:internal/streams/destroy"}}],"howMuchToRead node:internal/streams/readable":[{"file":"node:internal/streams/readable","fn":"howMuchToRead","id":"9","ix":"1","pos":"12215","caller":{"file":"node:internal/streams/readable","fn":"Readable.read","id":"9","ix":"-1","pos":"12692","key":"Readable.read node:internal/streams/readable"}}],"BufferList node:internal/streams/buffer_list":[{"file":"node:internal/streams/buffer_list","fn":"BufferList","id":"10","ix":"0","pos":"265","caller":{"file":"node:internal/streams/readable","fn":"ReadableState","id":"10","ix":"-1","pos":"2519","key":"ReadableState node:internal/streams/readable"}}],"getHighWaterMark node:internal/streams/state":[{"file":"node:internal/streams/state","fn":"getHighWaterMark","id":"10","ix":"1","pos":"424","caller":{"file":"node:internal/streams/readable","fn":"ReadableState","id":"10","ix":"-1","pos":"2519","key":"ReadableState node:internal/streams/readable"}}],"highWaterMarkFrom node:internal/streams/state":[{"file":"node:internal/streams/state","fn":"highWaterMarkFrom","id":"10","ix":"2","pos":"168","caller":{"file":"node:internal/streams/readable","fn":"ReadableState","id":"10","ix":"-1","pos":"2519","key":"ReadableState node:internal/streams/readable"}}],"checkListener node:events":[{"file":"node:events","fn":"checkListener","id":"12","ix":"0","pos":"7627","caller":{"file":"node:events","fn":"_addListener","id":"12","ix":"-1","pos":"16167","key":"_addListener node:events"}},{"file":"node:events","fn":"checkListener","id":"20","ix":"1","pos":"7627","caller":{"file":"node:events","fn":"addListener","id":"20","ix":"-1","pos":"18237","key":"addListener node:events"}},{"file":"node:events","fn":"checkListener","id":"41","ix":"3","pos":"7627","caller":{"file":"node:_http_server","fn":"detachSocket","id":"41","ix":"-1","pos":"9189","key":"detachSocket node:_http_server"}},{"file":"node:events","fn":"checkListener","id":"57","ix":"2","pos":"7627","caller":{"file":"node:internal/streams/readable","fn":"Readable.on","id":"57","ix":"-1","pos":"27748","key":"Readable.on node:internal/streams/readable"}}],"_getMaxListeners node:events":[{"file":"node:events","fn":"_getMaxListeners","id":"12","ix":"1","pos":"11869","caller":{"file":"node:events","fn":"_addListener","id":"12","ix":"-1","pos":"16167","key":"_addListener node:events"}},{"file":"node:events","fn":"_getMaxListeners","id":"20","ix":"2","pos":"11869","caller":{"file":"node:events","fn":"addListener","id":"20","ix":"-1","pos":"18237","key":"addListener node:events"}},{"file":"node:events","fn":"_getMaxListeners","id":"57","ix":"3","pos":"11869","caller":{"file":"node:internal/streams/readable","fn":"Readable.on","id":"57","ix":"-1","pos":"27748","key":"Readable.on node:internal/streams/readable"}}],"get node:events":[{"file":"node:events","fn":"get","id":"12","ix":"2","pos":"7780","caller":{"file":"node:events","fn":"_addListener","id":"12","ix":"-1","pos":"16167","key":"_addListener node:events"}},{"file":"node:events","fn":"get","id":"20","ix":"3","pos":"7780","caller":{"file":"node:events","fn":"addListener","id":"20","ix":"-1","pos":"18237","key":"addListener node:events"}},{"file":"node:events","fn":"get","id":"57","ix":"4","pos":"7780","caller":{"file":"node:internal/streams/readable","fn":"Readable.on","id":"57","ix":"-1","pos":"27748","key":"Readable.on node:internal/streams/readable"}}],"utcDate node:internal/http":[{"file":"node:internal/http","fn":"utcDate","id":"11","ix":"0","pos":"362","caller":{"file":"node:_http_outgoing","fn":"_storeHeader","id":"11","ix":"-1","pos":"11051","key":"_storeHeader node:_http_outgoing"}},{"file":"node:internal/http","fn":"utcDate","id":"66","ix":"0","pos":"362","caller":{"file":"node:_http_outgoing","fn":"_storeHeader","id":"66","ix":"-1","pos":"11051","key":"_storeHeader node:_http_outgoing"}}],"resume node:internal/streams/readable":[{"file":"node:internal/streams/readable","fn":"resume","id":"16","ix":"1","pos":"31104","caller":{"file":"node:internal/streams/readable","fn":"Readable.resume","id":"16","ix":"-1","pos":"30769","key":"Readable.resume node:internal/streams/readable"}},{"file":"node:internal/streams/readable","fn":"resume","id":"55","ix":"2","pos":"31104","caller":{"file":"node:net","fn":"Socket.resume","id":"55","ix":"-1","pos":"17240","key":"Socket.resume node:net"}}],"Socket.read node:net":[{"file":"node:net","fn":"Socket.read","id":"17","ix":"1","pos":"17452","caller":{"file":"node:internal/streams/readable","fn":"flow","id":"17","ix":"-1","pos":"31804","key":"flow node:internal/streams/readable"}},{"file":"node:net","fn":"Socket.read","id":"62","ix":"3","pos":"17452","caller":{"file":"node:internal/streams/readable","fn":"emitReadable_","id":"62","ix":"-1","pos":"18430","key":"emitReadable_ node:internal/streams/readable"}},{"file":"node:net","fn":"Socket.read","id":"68","ix":"3","pos":"17452","caller":{"file":"node:internal/streams/readable","fn":"resume_","id":"68","ix":"-1","pos":"31257","key":"resume_ node:internal/streams/readable"}}],"remove node:internal/linkedlist":[{"file":"node:internal/linkedlist","fn":"remove","id":"18","ix":"0","pos":"275","caller":{"file":"node:internal/linkedlist","fn":"append","id":"18","ix":"-1","pos":"558","key":"append node:internal/linkedlist"}},{"file":"node:internal/linkedlist","fn":"remove","id":"50","ix":"1","pos":"275","caller":{"file":"node:internal/timers","fn":"insert","id":"50","ix":"-1","pos":"10384","key":"insert node:internal/timers"}},{"file":"node:internal/linkedlist","fn":"remove","id":"49","ix":"7","pos":"275","caller":{"file":"node:internal/timers","fn":"listOnTimeout","id":"49","ix":"-1","pos":"14905","key":"listOnTimeout node:internal/timers"}},{"file":"node:internal/linkedlist","fn":"remove","id":"49","ix":"7","pos":"275","caller":{"file":"node:internal/timers","fn":"listOnTimeout","id":"49","ix":"-1","pos":"14905","key":"listOnTimeout node:internal/timers"}},{"file":"node:internal/linkedlist","fn":"remove","id":"61","ix":"9","pos":"275","caller":{"file":"file:///mnt/d/Software/JS_Expert/modulo12/02-memory-leak/02-memleak-events/index.js","fn":"onData","id":"61","ix":"-1","pos":"210","key":"onData file:///mnt/d/Software/JS_Expert/modulo12/02-memory-leak/02-memleak-events/index.js"}},{"file":"node:internal/linkedlist","fn":"remove","id":"70","ix":"1","pos":"275","caller":{"file":"node:internal/timers","fn":"insert","id":"70","ix":"-1","pos":"10384","key":"insert node:internal/timers"}},{"file":"node:internal/linkedlist","fn":"remove","id":"69","ix":"8","pos":"275","caller":{"file":"node:internal/timers","fn":"listOnTimeout","id":"69","ix":"-1","pos":"14905","key":"listOnTimeout node:internal/timers"}},{"file":"node:internal/linkedlist","fn":"remove","id":"69","ix":"8","pos":"275","caller":{"file":"node:internal/timers","fn":"listOnTimeout","id":"69","ix":"-1","pos":"14905","key":"listOnTimeout node:internal/timers"}},{"file":"node:internal/linkedlist","fn":"remove","id":"80","ix":"10","pos":"275","caller":{"file":"node:timers","fn":"setInterval","id":"80","ix":"-1","pos":"5786","key":"setInterval node:timers"}},{"file":"node:internal/linkedlist","fn":"remove","id":"83","ix":"10","pos":"275","caller":{"file":"node:internal/stream_base_commons","fn":"setStreamTimeout","id":"83","ix":"-1","pos":"6046","key":"setStreamTimeout node:internal/stream_base_commons"}},{"file":"node:internal/linkedlist","fn":"remove","id":"83","ix":"10","pos":"275","caller":{"file":"node:internal/stream_base_commons","fn":"setStreamTimeout","id":"83","ix":"-1","pos":"6046","key":"setStreamTimeout node:internal/stream_base_commons"}}],"_addListener node:events":[{"file":"node:events","fn":"_addListener","id":"20","ix":"0","pos":"16167","caller":{"file":"node:events","fn":"addListener","id":"20","ix":"-1","pos":"18237","key":"addListener node:events"}},{"file":"node:events","fn":"_addListener","id":"57","ix":"1","pos":"16167","caller":{"file":"node:internal/streams/readable","fn":"Readable.on","id":"57","ix":"-1","pos":"27748","key":"Readable.on node:internal/streams/readable"}}],"assert node:internal/assert":[{"file":"node:internal/assert","fn":"assert","id":"21","ix":"0","pos":"172","caller":{"file":"node:_http_server","fn":"assignSocket","id":"21","ix":"-1","pos":"8934","key":"assignSocket node:_http_server"}},{"file":"node:internal/assert","fn":"assert","id":"30","ix":"2","pos":"172","caller":{"file":"node:_http_server","fn":"_finish","id":"30","ix":"-1","pos":"7557","key":"_finish node:_http_server"}},{"file":"node:internal/assert","fn":"assert","id":"41","ix":"0","pos":"172","caller":{"file":"node:_http_server","fn":"detachSocket","id":"41","ix":"-1","pos":"9189","key":"detachSocket node:_http_server"}},{"file":"node:internal/assert","fn":"assert","id":"45","ix":"1","pos":"172","caller":{"file":"node:_http_server","fn":"resOnFinish","id":"45","ix":"-1","pos":"26108","key":"resOnFinish node:_http_server"}}],"_flush node:_http_outgoing":[{"file":"node:_http_outgoing","fn":"_flush","id":"21","ix":"1","pos":"27116","caller":{"file":"node:_http_server","fn":"assignSocket","id":"21","ix":"-1","pos":"8934","key":"assignSocket node:_http_server"}}],"emit node:events":[{"file":"node:events","fn":"emit","id":"21","ix":"2","pos":"13881","caller":{"file":"node:_http_server","fn":"assignSocket","id":"21","ix":"-1","pos":"8934","key":"assignSocket node:_http_server"}},{"file":"node:events","fn":"emit","id":"25","ix":"2","pos":"13881","caller":{"file":"node:internal/streams/readable","fn":"endReadableNT","id":"25","ix":"-1","pos":"39299","key":"endReadableNT node:internal/streams/readable"}},{"file":"node:events","fn":"emit","id":"26","ix":"3","pos":"13881","caller":{"file":"node:_http_server","fn":"parserOnIncoming","id":"26","ix":"-1","pos":"28043","key":"parserOnIncoming node:_http_server"}},{"file":"node:events","fn":"emit","id":"30","ix":"5","pos":"13881","caller":{"file":"node:_http_server","fn":"_finish","id":"30","ix":"-1","pos":"7557","key":"_finish node:_http_server"}},{"file":"node:events","fn":"emit","id":"39","ix":"0","pos":"13881","caller":{"file":"node:internal/streams/destroy","fn":"emitCloseNT","id":"39","ix":"-1","pos":"2515","key":"emitCloseNT node:internal/streams/destroy"}},{"file":"node:events","fn":"emit","id":"43","ix":"0","pos":"13881","caller":{"file":"file:///mnt/d/Software/JS_Expert/modulo12/02-memory-leak/02-memleak-events/index.js","fn":"handler","id":"43","ix":"-1","pos":"382","key":"handler file:///mnt/d/Software/JS_Expert/modulo12/02-memory-leak/02-memleak-events/index.js"}},{"file":"node:events","fn":"emit","id":"60","ix":"0","pos":"13881","caller":{"file":"node:_http_outgoing","fn":"onFinish","id":"60","ix":"-1","pos":"24267","key":"onFinish node:_http_outgoing"}},{"file":"node:events","fn":"emit","id":"62","ix":"2","pos":"13881","caller":{"file":"node:internal/streams/readable","fn":"emitReadable_","id":"62","ix":"-1","pos":"18430","key":"emitReadable_ node:internal/streams/readable"}},{"file":"node:events","fn":"emit","id":"68","ix":"2","pos":"13881","caller":{"file":"node:internal/streams/readable","fn":"resume_","id":"68","ix":"-1","pos":"31257","key":"resume_ node:internal/streams/readable"}},{"file":"node:events","fn":"emit","id":"73","ix":"0","pos":"13881","caller":{"file":"node:_http_server","fn":"emitCloseNT","id":"73","ix":"-1","pos":"27772","key":"emitCloseNT node:_http_server"}}],"socketListenerWrap node:_http_server":[{"file":"node:_http_server","fn":"socketListenerWrap","id":"21","ix":"3","pos":"32196","caller":{"file":"node:_http_server","fn":"assignSocket","id":"21","ix":"-1","pos":"8934","key":"assignSocket node:_http_server"}}],"_flushOutput node:_http_outgoing":[{"file":"node:_http_outgoing","fn":"_flushOutput","id":"21","ix":"4","pos":"27596","caller":{"file":"node:_http_server","fn":"assignSocket","id":"21","ix":"-1","pos":"8934","key":"assignSocket node:_http_server"}}],"Writable.cork node:internal/streams/writable":[{"file":"node:internal/streams/writable","fn":"Writable.cork","id":"21","ix":"5","pos":"10864","caller":{"file":"node:_http_server","fn":"assignSocket","id":"21","ix":"-1","pos":"8934","key":"assignSocket node:_http_server"}}],"Writable.write node:internal/streams/writable":[{"file":"node:internal/streams/writable","fn":"Writable.write","id":"21","ix":"6","pos":"10749","caller":{"file":"node:_http_server","fn":"assignSocket","id":"21","ix":"-1","pos":"8934","key":"assignSocket node:_http_server"}}],"Writable.uncork node:internal/streams/writable":[{"file":"node:internal/streams/writable","fn":"Writable.uncork","id":"21","ix":"7","pos":"10941","caller":{"file":"node:_http_server","fn":"assignSocket","id":"21","ix":"-1","pos":"8934","key":"assignSocket node:_http_server"}}],"hasTickScheduled node:internal/process/task_queues":[{"file":"node:internal/process/task_queues","fn":"hasTickScheduled","id":"23","ix":"0","pos":"1024","caller":{"file":"node:internal/process/task_queues","fn":"runNextTicks","id":"23","ix":"-1","pos":"1285","key":"runNextTicks node:internal/process/task_queues"}},{"file":"node:internal/process/task_queues","fn":"hasTickScheduled","id":"23","ix":"0","pos":"1024","caller":{"file":"node:internal/process/task_queues","fn":"runNextTicks","id":"23","ix":"-1","pos":"1285","key":"runNextTicks node:internal/process/task_queues"}}],"hasRejectionToWarn node:internal/process/promises":[{"file":"node:internal/process/promises","fn":"hasRejectionToWarn","id":"23","ix":"1","pos":"2184","caller":{"file":"node:internal/process/task_queues","fn":"runNextTicks","id":"23","ix":"-1","pos":"1285","key":"runNextTicks node:internal/process/task_queues"}},{"file":"node:internal/process/promises","fn":"hasRejectionToWarn","id":"23","ix":"1","pos":"2184","caller":{"file":"node:internal/process/task_queues","fn":"runNextTicks","id":"23","ix":"-1","pos":"1285","key":"runNextTicks node:internal/process/task_queues"}}],"socketOnDrain node:_http_server":[{"file":"node:_http_server","fn":"socketOnDrain","id":"24","ix":"0","pos":"19407","caller":{"file":"node:_http_server","fn":"updateOutgoingData","id":"24","ix":"-1","pos":"19294","key":"updateOutgoingData node:_http_server"}}],"get node:internal/streams/writable":[{"file":"node:internal/streams/writable","fn":"get","id":"24","ix":"1","pos":"23967","caller":{"file":"node:_http_server","fn":"updateOutgoingData","id":"24","ix":"-1","pos":"19294","key":"updateOutgoingData node:_http_server"}},{"file":"node:internal/streams/writable","fn":"get","id":"26","ix":"0","pos":"23967","caller":{"file":"node:_http_server","fn":"parserOnIncoming","id":"26","ix":"-1","pos":"28043","key":"parserOnIncoming node:_http_server"}},{"file":"node:internal/streams/writable","fn":"get","id":"40","ix":"5","pos":"22736","caller":{"file":"node:_http_outgoing","fn":"write_","id":"40","ix":"-1","pos":"21766","key":"write_ node:_http_outgoing"}},{"file":"node:internal/streams/writable","fn":"get","id":"42","ix":"0","pos":"22736","caller":{"file":"node:_http_outgoing","fn":"_writeRaw","id":"42","ix":"-1","pos":"10151","key":"_writeRaw node:_http_outgoing"}},{"file":"node:internal/streams/writable","fn":"get","id":"53","ix":"1","pos":"24193","caller":{"file":"node:_http_outgoing","fn":"end","id":"53","ix":"-1","pos":"24416","key":"end node:_http_outgoing"}},{"file":"node:internal/streams/writable","fn":"get","id":"53","ix":"5","pos":"22736","caller":{"file":"node:_http_outgoing","fn":"end","id":"53","ix":"-1","pos":"24416","key":"end node:_http_outgoing"}}],"destroy node:internal/streams/destroy":[{"file":"node:internal/streams/destroy","fn":"destroy","id":"25","ix":"1","pos":"672","caller":{"file":"node:internal/streams/readable","fn":"endReadableNT","id":"25","ix":"-1","pos":"39299","key":"endReadableNT node:internal/streams/readable"}}],"_destroy node:internal/streams/destroy":[{"file":"node:internal/streams/destroy","fn":"_destroy","id":"25","ix":"3","pos":"1474","caller":{"file":"node:internal/streams/readable","fn":"endReadableNT","id":"25","ix":"-1","pos":"39299","key":"endReadableNT node:internal/streams/readable"}}],"checkError node:internal/streams/destroy":[{"file":"node:internal/streams/destroy","fn":"checkError","id":"25","ix":"4","pos":"254","caller":{"file":"node:internal/streams/readable","fn":"endReadableNT","id":"25","ix":"-1","pos":"39299","key":"endReadableNT node:internal/streams/readable"}},{"file":"node:internal/streams/destroy","fn":"checkError","id":"64","ix":"7","pos":"254","caller":{"file":"node:internal/streams/destroy","fn":"onDestroy","id":"64","ix":"-1","pos":"1535","key":"onDestroy node:internal/streams/destroy"}},{"file":"node:internal/streams/destroy","fn":"checkError","id":"72","ix":"2","pos":"254","caller":{"file":"node:_http_incoming","fn":"onError","id":"72","ix":"-1","pos":"12652","key":"onError node:_http_incoming"}}],"_destroy node:_http_incoming":[{"file":"node:_http_incoming","fn":"_destroy","id":"25","ix":"5","pos":"5158","caller":{"file":"node:internal/streams/readable","fn":"endReadableNT","id":"25","ix":"-1","pos":"39299","key":"endReadableNT node:internal/streams/readable"}}],"get node:internal/streams/readable":[{"file":"node:internal/streams/readable","fn":"get","id":"25","ix":"6","pos":"37773","caller":{"file":"node:internal/streams/readable","fn":"endReadableNT","id":"25","ix":"-1","pos":"39299","key":"endReadableNT node:internal/streams/readable"}},{"file":"node:internal/streams/readable","fn":"get","id":"33","ix":"3","pos":"36405","caller":{"file":"node:_http_common","fn":"parserOnHeadersComplete","id":"33","ix":"-1","pos":"2931","key":"parserOnHeadersComplete node:_http_common"}},{"file":"node:internal/streams/readable","fn":"get","id":"47","ix":"0","pos":"37773","caller":{"file":"node:_http_server","fn":"clearIncoming","id":"47","ix":"-1","pos":"25199","key":"clearIncoming node:_http_server"}},{"file":"node:internal/streams/readable","fn":"get","id":"45","ix":"10","pos":"37773","caller":{"file":"node:_http_server","fn":"resOnFinish","id":"45","ix":"-1","pos":"26108","key":"resOnFinish node:_http_server"}},{"file":"node:internal/streams/readable","fn":"get","id":"71","ix":"0","pos":"35417","caller":{"file":"node:_http_incoming","fn":"readStart","id":"71","ix":"-1","pos":"1557","key":"readStart node:_http_incoming"}},{"file":"node:internal/streams/readable","fn":"get","id":"76","ix":"2","pos":"35417","caller":{"file":"node:_http_common","fn":"parserOnMessageComplete","id":"76","ix":"-1","pos":"4908","key":"parserOnMessageComplete node:_http_common"}}],"DTRACE_HTTP_SERVER_REQUEST node:internal/dtrace":[{"file":"node:internal/dtrace","fn":"DTRACE_HTTP_SERVER_REQUEST","id":"26","ix":"1","pos":"180","caller":{"file":"node:_http_server","fn":"parserOnIncoming","id":"26","ix":"-1","pos":"28043","key":"parserOnIncoming node:_http_server"}}],"get hasSubscribers node:diagnostics_channel":[{"file":"node:diagnostics_channel","fn":"get hasSubscribers","id":"26","ix":"2","pos":"1991","caller":{"file":"node:_http_server","fn":"parserOnIncoming","id":"26","ix":"-1","pos":"28043","key":"parserOnIncoming node:_http_server"}},{"file":"node:diagnostics_channel","fn":"get hasSubscribers","id":"45","ix":"0","pos":"1991","caller":{"file":"node:_http_server","fn":"resOnFinish","id":"45","ix":"-1","pos":"26108","key":"resOnFinish node:_http_server"}}],"Readable.on node:internal/streams/readable":[{"file":"node:internal/streams/readable","fn":"Readable.on","id":"26","ix":"4","pos":"27748","caller":{"file":"node:_http_server","fn":"parserOnIncoming","id":"26","ix":"-1","pos":"28043","key":"parserOnIncoming node:_http_server"}}],"ServerResponse node:_http_server":[{"file":"node:_http_server","fn":"ServerResponse","id":"26","ix":"5","pos":"6785","caller":{"file":"node:_http_server","fn":"parserOnIncoming","id":"26","ix":"-1","pos":"28043","key":"parserOnIncoming node:_http_server"}}],"hasObserver node:internal/perf/observe":[{"file":"node:internal/perf/observe","fn":"hasObserver","id":"26","ix":"6","pos":"11617","caller":{"file":"node:_http_server","fn":"parserOnIncoming","id":"26","ix":"-1","pos":"28043","key":"parserOnIncoming node:_http_server"}},{"file":"node:internal/perf/observe","fn":"hasObserver","id":"30","ix":"4","pos":"11617","caller":{"file":"node:_http_server","fn":"_finish","id":"30","ix":"-1","pos":"7557","key":"_finish node:_http_server"}}],"resetSocketTimeout node:_http_server":[{"file":"node:_http_server","fn":"resetSocketTimeout","id":"26","ix":"7","pos":"31027","caller":{"file":"node:_http_server","fn":"parserOnIncoming","id":"26","ix":"-1","pos":"28043","key":"parserOnIncoming node:_http_server"}},{"file":"node:_http_server","fn":"resetSocketTimeout","id":"87","ix":"0","pos":"31027","caller":{"file":"node:_http_server","fn":"onParserExecuteCommon","id":"87","ix":"-1","pos":"23259","key":"onParserExecuteCommon node:_http_server"}}],"getObserverType node:internal/perf/observe":[{"file":"node:internal/perf/observe","fn":"getObserverType","id":"26","ix":"8","pos":"2430","caller":{"file":"node:_http_server","fn":"parserOnIncoming","id":"26","ix":"-1","pos":"28043","key":"parserOnIncoming node:_http_server"}},{"file":"node:internal/perf/observe","fn":"getObserverType","id":"30","ix":"6","pos":"2430","caller":{"file":"node:_http_server","fn":"_finish","id":"30","ix":"-1","pos":"7557","key":"_finish node:_http_server"}}],"checkInvalidHeaderChar node:_http_common":[{"file":"node:_http_common","fn":"checkInvalidHeaderChar","id":"27","ix":"0","pos":"7274","caller":{"file":"node:_http_server","fn":"writeHead","id":"27","ix":"-1","pos":"9836","key":"writeHead node:_http_server"}}],"DTRACE_HTTP_SERVER_RESPONSE node:internal/dtrace":[{"file":"node:internal/dtrace","fn":"DTRACE_HTTP_SERVER_RESPONSE","id":"30","ix":"0","pos":"222","caller":{"file":"node:_http_server","fn":"_finish","id":"30","ix":"-1","pos":"7557","key":"_finish node:_http_server"}}],"_finish node:_http_outgoing":[{"file":"node:_http_outgoing","fn":"_finish","id":"30","ix":"1","pos":"26245","caller":{"file":"node:_http_server","fn":"_finish","id":"30","ix":"-1","pos":"7557","key":"_finish node:_http_server"}}],"emitStatistics node:internal/http":[{"file":"node:internal/http","fn":"emitStatistics","id":"30","ix":"3","pos":"648","caller":{"file":"node:_http_server","fn":"_finish","id":"30","ix":"-1","pos":"7557","key":"_finish node:_http_server"}}],"writeOrBuffer node:internal/streams/writable":[{"file":"node:internal/streams/writable","fn":"writeOrBuffer","id":"29","ix":"0","pos":"11668","caller":{"file":"node:internal/streams/writable","fn":"_write","id":"29","ix":"-1","pos":"9383","key":"_write node:internal/streams/writable"}},{"file":"node:internal/streams/writable","fn":"writeOrBuffer","id":"85","ix":"1","pos":"11668","caller":{"file":"node:internal/streams/writable","fn":"Writable.write","id":"85","ix":"-1","pos":"10749","key":"Writable.write node:internal/streams/writable"}}],"isEncoding node:buffer":[{"file":"node:buffer","fn":"isEncoding","id":"29","ix":"1","pos":"14808","caller":{"file":"node:internal/streams/writable","fn":"_write","id":"29","ix":"-1","pos":"9383","key":"_write node:internal/streams/writable"}},{"file":"node:buffer","fn":"isEncoding","id":"85","ix":"2","pos":"14808","caller":{"file":"node:internal/streams/writable","fn":"Writable.write","id":"85","ix":"-1","pos":"10749","key":"Writable.write node:internal/streams/writable"}}],"normalizeEncoding node:internal/util":[{"file":"node:internal/util","fn":"normalizeEncoding","id":"29","ix":"2","pos":"4206","caller":{"file":"node:internal/streams/writable","fn":"_write","id":"29","ix":"-1","pos":"9383","key":"_write node:internal/streams/writable"}},{"file":"node:internal/util","fn":"normalizeEncoding","id":"85","ix":"3","pos":"4206","caller":{"file":"node:internal/streams/writable","fn":"Writable.write","id":"85","ix":"-1","pos":"10749","key":"Writable.write node:internal/streams/writable"}}],"Stream node:internal/streams/legacy":[{"file":"node:internal/streams/legacy","fn":"Stream","id":"32","ix":"0","pos":"127","caller":{"file":"node:_http_outgoing","fn":"OutgoingMessage","id":"32","ix":"-1","pos":"3185","key":"OutgoingMessage node:_http_outgoing"}},{"file":"node:internal/streams/legacy","fn":"Stream","id":"33","ix":"5","pos":"127","caller":{"file":"node:_http_common","fn":"parserOnHeadersComplete","id":"33","ix":"-1","pos":"2931","key":"parserOnHeadersComplete node:_http_common"}}],"EventEmitter node:events":[{"file":"node:events","fn":"EventEmitter","id":"32","ix":"1","pos":"6267","caller":{"file":"node:_http_outgoing","fn":"OutgoingMessage","id":"32","ix":"-1","pos":"3185","key":"OutgoingMessage node:_http_outgoing"}},{"file":"node:events","fn":"EventEmitter","id":"33","ix":"6","pos":"6267","caller":{"file":"node:_http_common","fn":"parserOnHeadersComplete","id":"33","ix":"-1","pos":"2931","key":"parserOnHeadersComplete node:_http_common"}}],"EventEmitter.init node:events":[{"file":"node:events","fn":"EventEmitter.init","id":"32","ix":"2","pos":"9680","caller":{"file":"node:_http_outgoing","fn":"OutgoingMessage","id":"32","ix":"-1","pos":"3185","key":"OutgoingMessage node:_http_outgoing"}},{"file":"node:events","fn":"EventEmitter.init","id":"33","ix":"8","pos":"9680","caller":{"file":"node:_http_common","fn":"parserOnHeadersComplete","id":"33","ix":"-1","pos":"2931","key":"parserOnHeadersComplete node:_http_common"}}],"_addHeaderLines node:_http_incoming":[{"file":"node:_http_incoming","fn":"_addHeaderLines","id":"33","ix":"1","pos":"5909","caller":{"file":"node:_http_common","fn":"parserOnHeadersComplete","id":"33","ix":"-1","pos":"2931","key":"parserOnHeadersComplete node:_http_common"}}],"IncomingMessage node:_http_incoming":[{"file":"node:_http_incoming","fn":"IncomingMessage","id":"33","ix":"2","pos":"1797","caller":{"file":"node:_http_common","fn":"parserOnHeadersComplete","id":"33","ix":"-1","pos":"2931","key":"parserOnHeadersComplete node:_http_common"}}],"Readable node:internal/streams/readable":[{"file":"node:internal/streams/readable","fn":"Readable","id":"33","ix":"4","pos":"6246","caller":{"file":"node:_http_common","fn":"parserOnHeadersComplete","id":"33","ix":"-1","pos":"2931","key":"parserOnHeadersComplete node:_http_common"}}],"construct node:internal/streams/destroy":[{"file":"node:internal/streams/destroy","fn":"construct","id":"33","ix":"7","pos":"4626","caller":{"file":"node:_http_common","fn":"parserOnHeadersComplete","id":"33","ix":"-1","pos":"2931","key":"parserOnHeadersComplete node:_http_common"}}],"afterWriteDispatched node:internal/stream_base_commons":[{"file":"node:internal/stream_base_commons","fn":"afterWriteDispatched","id":"36","ix":"0","pos":"3812","caller":{"file":"node:internal/stream_base_commons","fn":"writevGeneric","id":"36","ix":"-1","pos":"2957","key":"writevGeneric node:internal/stream_base_commons"}},{"file":"node:internal/stream_base_commons","fn":"afterWriteDispatched","id":"35","ix":"6","pos":"3812","caller":{"file":"node:internal/streams/writable","fn":"clearBuffer","id":"35","ix":"-1","pos":"16266","key":"clearBuffer node:internal/streams/writable"}}],"createWriteWrap node:internal/stream_base_commons":[{"file":"node:internal/stream_base_commons","fn":"createWriteWrap","id":"36","ix":"1","pos":"2719","caller":{"file":"node:internal/stream_base_commons","fn":"writevGeneric","id":"36","ix":"-1","pos":"2957","key":"writevGeneric node:internal/stream_base_commons"}},{"file":"node:internal/stream_base_commons","fn":"createWriteWrap","id":"35","ix":"8","pos":"2719","caller":{"file":"node:internal/streams/writable","fn":"clearBuffer","id":"35","ix":"-1","pos":"16266","key":"clearBuffer node:internal/streams/writable"}}],"resetBuffer node:internal/streams/writable":[{"file":"node:internal/streams/writable","fn":"resetBuffer","id":"35","ix":"0","pos":"7005","caller":{"file":"node:internal/streams/writable","fn":"clearBuffer","id":"35","ix":"-1","pos":"16266","key":"clearBuffer node:internal/streams/writable"}}],"doWrite node:internal/streams/writable":[{"file":"node:internal/streams/writable","fn":"doWrite","id":"35","ix":"1","pos":"12677","caller":{"file":"node:internal/streams/writable","fn":"clearBuffer","id":"35","ix":"-1","pos":"16266","key":"clearBuffer node:internal/streams/writable"}}],"Socket._writev node:net":[{"file":"node:net","fn":"Socket._writev","id":"35","ix":"2","pos":"21262","caller":{"file":"node:internal/streams/writable","fn":"clearBuffer","id":"35","ix":"-1","pos":"16266","key":"clearBuffer node:internal/streams/writable"}}],"Socket._writeGeneric node:net":[{"file":"node:net","fn":"Socket._writeGeneric","id":"35","ix":"3","pos":"20470","caller":{"file":"node:internal/streams/writable","fn":"clearBuffer","id":"35","ix":"-1","pos":"16266","key":"clearBuffer node:internal/streams/writable"}}],"get node:net":[{"file":"node:net","fn":"get","id":"35","ix":"4","pos":"46980","caller":{"file":"node:internal/streams/writable","fn":"clearBuffer","id":"35","ix":"-1","pos":"16266","key":"clearBuffer node:internal/streams/writable"}}],"writevGeneric node:internal/stream_base_commons":[{"file":"node:internal/stream_base_commons","fn":"writevGeneric","id":"35","ix":"5","pos":"2957","caller":{"file":"node:internal/streams/writable","fn":"clearBuffer","id":"35","ix":"-1","pos":"16266","key":"clearBuffer node:internal/streams/writable"}}],"_unrefTimer node:net":[{"file":"node:net","fn":"_unrefTimer","id":"35","ix":"7","pos":"11830","caller":{"file":"node:internal/streams/writable","fn":"clearBuffer","id":"35","ix":"-1","pos":"16266","key":"clearBuffer node:internal/streams/writable"}},{"file":"node:net","fn":"_unrefTimer","id":"84","ix":"1","pos":"11830","caller":{"file":"node:_http_server","fn":"onParserExecute","id":"84","ix":"-1","pos":"21546","key":"onParserExecute node:_http_server"}}],"Timeout.refresh node:internal/timers":[{"file":"node:internal/timers","fn":"Timeout.refresh","id":"35","ix":"9","pos":"7082","caller":{"file":"node:internal/streams/writable","fn":"clearBuffer","id":"35","ix":"-1","pos":"16266","key":"clearBuffer node:internal/streams/writable"}},{"file":"node:internal/timers","fn":"Timeout.refresh","id":"74","ix":"0","pos":"7082","caller":{"file":"node:net","fn":"_unrefTimer","id":"74","ix":"-1","pos":"11830","key":"_unrefTimer node:net"}},{"file":"node:internal/timers","fn":"Timeout.refresh","id":"84","ix":"2","pos":"7082","caller":{"file":"node:_http_server","fn":"onParserExecute","id":"84","ix":"-1","pos":"21546","key":"onParserExecute node:_http_server"}}],"unrefActive node:internal/timers":[{"file":"node:internal/timers","fn":"unrefActive","id":"35","ix":"10","pos":"9590","caller":{"file":"node:internal/streams/writable","fn":"clearBuffer","id":"35","ix":"-1","pos":"16266","key":"clearBuffer node:internal/streams/writable"}},{"file":"node:internal/timers","fn":"unrefActive","id":"74","ix":"1","pos":"9590","caller":{"file":"node:net","fn":"_unrefTimer","id":"74","ix":"-1","pos":"11830","key":"_unrefTimer node:net"}},{"file":"node:internal/timers","fn":"unrefActive","id":"84","ix":"3","pos":"9590","caller":{"file":"node:_http_server","fn":"onParserExecute","id":"84","ix":"-1","pos":"21546","key":"onParserExecute node:_http_server"}}],"_addHeaderLine node:_http_incoming":[{"file":"node:_http_incoming","fn":"_addHeaderLine","id":"37","ix":"0","pos":"11594","caller":{"file":"node:_http_incoming","fn":"get","id":"37","ix":"-1","pos":"3083","key":"get node:_http_incoming"}}],"Readable.removeListener node:internal/streams/readable":[{"file":"node:internal/streams/readable","fn":"Readable.removeListener","id":"41","ix":"1","pos":"28750","caller":{"file":"node:_http_server","fn":"detachSocket","id":"41","ix":"-1","pos":"9189","key":"detachSocket node:_http_server"}}],"removeListener node:events":[{"file":"node:events","fn":"removeListener","id":"41","ix":"2","pos":"20159","caller":{"file":"node:_http_server","fn":"detachSocket","id":"41","ix":"-1","pos":"9189","key":"detachSocket node:_http_server"}}],"spliceOne node:internal/util":[{"file":"node:internal/util","fn":"spliceOne","id":"41","ix":"4","pos":"10925","caller":{"file":"node:_http_server","fn":"detachSocket","id":"41","ix":"-1","pos":"9189","key":"detachSocket node:_http_server"}}],"_implicitHeader node:_http_server":[{"file":"node:_http_server","fn":"_implicitHeader","id":"40","ix":"0","pos":"9726","caller":{"file":"node:_http_outgoing","fn":"write_","id":"40","ix":"-1","pos":"21766","key":"write_ node:_http_outgoing"}}],"_send node:_http_outgoing":[{"file":"node:_http_outgoing","fn":"_send","id":"40","ix":"2","pos":"9347","caller":{"file":"node:_http_outgoing","fn":"write_","id":"40","ix":"-1","pos":"21766","key":"write_ node:_http_outgoing"}},{"file":"node:_http_outgoing","fn":"_send","id":"53","ix":"3","pos":"9347","caller":{"file":"node:_http_outgoing","fn":"end","id":"53","ix":"-1","pos":"24416","key":"end node:_http_outgoing"}}],"byteLength node:buffer":[{"file":"node:buffer","fn":"byteLength","id":"40","ix":"3","pos":"21787","caller":{"file":"node:_http_outgoing","fn":"write_","id":"40","ix":"-1","pos":"21766","key":"write_ node:_http_outgoing"}}],"_writeRaw node:_http_outgoing":[{"file":"node:_http_outgoing","fn":"_writeRaw","id":"40","ix":"4","pos":"10151","caller":{"file":"node:_http_outgoing","fn":"write_","id":"40","ix":"-1","pos":"21766","key":"write_ node:_http_outgoing"}},{"file":"node:_http_outgoing","fn":"_writeRaw","id":"53","ix":"4","pos":"10151","caller":{"file":"node:_http_outgoing","fn":"end","id":"53","ix":"-1","pos":"24416","key":"end node:_http_outgoing"}}],"get node:internal/streams/duplex":[{"file":"node:internal/streams/duplex","fn":"get","id":"40","ix":"6","pos":"3274","caller":{"file":"node:_http_outgoing","fn":"write_","id":"40","ix":"-1","pos":"21766","key":"write_ node:_http_outgoing"}},{"file":"node:internal/streams/duplex","fn":"get","id":"42","ix":"1","pos":"3274","caller":{"file":"node:_http_outgoing","fn":"_writeRaw","id":"42","ix":"-1","pos":"10151","key":"_writeRaw node:_http_outgoing"}},{"file":"node:internal/streams/duplex","fn":"get","id":"46","ix":"4","pos":"3274","caller":{"file":"node:internal/streams/writable","fn":"afterWriteTick","id":"46","ix":"-1","pos":"15092","key":"afterWriteTick node:internal/streams/writable"}},{"file":"node:internal/streams/duplex","fn":"get","id":"53","ix":"6","pos":"3274","caller":{"file":"node:_http_outgoing","fn":"end","id":"53","ix":"-1","pos":"24416","key":"end node:_http_outgoing"}},{"file":"node:internal/streams/duplex","fn":"get","id":"83","ix":"11","pos":"3274","caller":{"file":"node:internal/stream_base_commons","fn":"setStreamTimeout","id":"83","ix":"-1","pos":"6046","key":"setStreamTimeout node:internal/stream_base_commons"}}],"initAsyncResource node:internal/timers":[{"file":"node:internal/timers","fn":"initAsyncResource","id":"44","ix":"0","pos":"5425","caller":{"file":"node:internal/timers","fn":"Timeout","id":"44","ix":"-1","pos":"5778","key":"Timeout node:internal/timers"}},{"file":"node:internal/timers","fn":"initAsyncResource","id":"80","ix":"4","pos":"5425","caller":{"file":"node:timers","fn":"setInterval","id":"80","ix":"-1","pos":"5786","key":"setInterval node:timers"}}],"incRefCount node:internal/timers":[{"file":"node:internal/timers","fn":"incRefCount","id":"44","ix":"5","pos":"9151","caller":{"file":"node:internal/timers","fn":"Timeout","id":"44","ix":"-1","pos":"5778","key":"Timeout node:internal/timers"}},{"file":"node:internal/timers","fn":"incRefCount","id":"80","ix":"9","pos":"9151","caller":{"file":"node:timers","fn":"setInterval","id":"80","ix":"-1","pos":"5786","key":"setInterval node:timers"}}],"afterWrite node:internal/streams/writable":[{"file":"node:internal/streams/writable","fn":"afterWrite","id":"46","ix":"0","pos":"15229","caller":{"file":"node:internal/streams/writable","fn":"afterWriteTick","id":"46","ix":"-1","pos":"15092","key":"afterWriteTick node:internal/streams/writable"}}],"finishMaybe node:internal/streams/writable":[{"file":"node:internal/streams/writable","fn":"finishMaybe","id":"46","ix":"1","pos":"21346","caller":{"file":"node:internal/streams/writable","fn":"afterWriteTick","id":"46","ix":"-1","pos":"15092","key":"afterWriteTick node:internal/streams/writable"}}],"callback node:internal/streams/writable":[{"file":"node:internal/streams/writable","fn":"callback","id":"46","ix":"2","pos":"16758","caller":{"file":"node:internal/streams/writable","fn":"afterWriteTick","id":"46","ix":"-1","pos":"15092","key":"afterWriteTick node:internal/streams/writable"}}],"needFinish node:internal/streams/writable":[{"file":"node:internal/streams/writable","fn":"needFinish","id":"46","ix":"3","pos":"19361","caller":{"file":"node:internal/streams/writable","fn":"afterWriteTick","id":"46","ix":"-1","pos":"15092","key":"afterWriteTick node:internal/streams/writable"}}],"validateNumber node:internal/validators":[{"file":"node:internal/validators","fn":"validateNumber","id":"48","ix":"0","pos":"3551","caller":{"file":"node:internal/crypto/random","fn":"assertSize","id":"48","ix":"-1","pos":"1499","key":"assertSize node:internal/crypto/random"}},{"file":"node:internal/validators","fn":"validateNumber","id":"54","ix":"2","pos":"3551","caller":{"file":"node:internal/crypto/random","fn":"randomFillSync","id":"54","ix":"-1","pos":"2499","key":"randomFillSync node:internal/crypto/random"}},{"file":"node:internal/validators","fn":"validateNumber","id":"54","ix":"2","pos":"3551","caller":{"file":"node:internal/crypto/random","fn":"randomFillSync","id":"54","ix":"-1","pos":"2499","key":"randomFillSync node:internal/crypto/random"}},{"file":"node:internal/validators","fn":"validateNumber","id":"61","ix":"8","pos":"3551","caller":{"file":"file:///mnt/d/Software/JS_Expert/modulo12/02-memory-leak/02-memleak-events/index.js","fn":"onData","id":"61","ix":"-1","pos":"210","key":"onData file:///mnt/d/Software/JS_Expert/modulo12/02-memory-leak/02-memleak-events/index.js"}},{"file":"node:internal/validators","fn":"validateNumber","id":"79","ix":"3","pos":"3551","caller":{"file":"node:internal/crypto/random","fn":"randomBytes","id":"79","ix":"-1","pos":"1963","key":"randomBytes node:internal/crypto/random"}},{"file":"node:internal/validators","fn":"validateNumber","id":"79","ix":"3","pos":"3551","caller":{"file":"node:internal/crypto/random","fn":"randomBytes","id":"79","ix":"-1","pos":"1963","key":"randomBytes node:internal/crypto/random"}},{"file":"node:internal/validators","fn":"validateNumber","id":"79","ix":"3","pos":"3551","caller":{"file":"node:internal/crypto/random","fn":"randomBytes","id":"79","ix":"-1","pos":"1963","key":"randomBytes node:internal/crypto/random"}},{"file":"node:internal/validators","fn":"validateNumber","id":"83","ix":"2","pos":"3551","caller":{"file":"node:internal/stream_base_commons","fn":"setStreamTimeout","id":"83","ix":"-1","pos":"6046","key":"setStreamTimeout node:internal/stream_base_commons"}}],"clearIncoming node:_http_server":[{"file":"node:_http_server","fn":"clearIncoming","id":"45","ix":"9","pos":"25199","caller":{"file":"node:_http_server","fn":"resOnFinish","id":"45","ix":"-1","pos":"26108","key":"resOnFinish node:_http_server"}}],"clearRequestTimeout node:_http_server":[{"file":"node:_http_server","fn":"clearRequestTimeout","id":"45","ix":"11","pos":"25879","caller":{"file":"node:_http_server","fn":"resOnFinish","id":"45","ix":"-1","pos":"26108","key":"resOnFinish node:_http_server"}}],"_dump node:_http_incoming":[{"file":"node:_http_incoming","fn":"_dump","id":"45","ix":"12","pos":"12406","caller":{"file":"node:_http_server","fn":"resOnFinish","id":"45","ix":"-1","pos":"26108","key":"resOnFinish node:_http_server"}}],"Readable.removeAllListeners node:internal/streams/readable":[{"file":"node:internal/streams/readable","fn":"Readable.removeAllListeners","id":"45","ix":"13","pos":"29418","caller":{"file":"node:_http_server","fn":"resOnFinish","id":"45","ix":"-1","pos":"26108","key":"resOnFinish node:_http_server"}}],"append node:internal/linkedlist":[{"file":"node:internal/linkedlist","fn":"append","id":"50","ix":"0","pos":"558","caller":{"file":"node:internal/timers","fn":"insert","id":"50","ix":"-1","pos":"10384","key":"insert node:internal/timers"}},{"file":"node:internal/linkedlist","fn":"append","id":"49","ix":"8","pos":"558","caller":{"file":"node:internal/timers","fn":"listOnTimeout","id":"49","ix":"-1","pos":"14905","key":"listOnTimeout node:internal/timers"}},{"file":"node:internal/linkedlist","fn":"append","id":"61","ix":"5","pos":"558","caller":{"file":"file:///mnt/d/Software/JS_Expert/modulo12/02-memory-leak/02-memleak-events/index.js","fn":"onData","id":"61","ix":"-1","pos":"210","key":"onData file:///mnt/d/Software/JS_Expert/modulo12/02-memory-leak/02-memleak-events/index.js"}},{"file":"node:internal/linkedlist","fn":"append","id":"70","ix":"0","pos":"558","caller":{"file":"node:internal/timers","fn":"insert","id":"70","ix":"-1","pos":"10384","key":"insert node:internal/timers"}},{"file":"node:internal/linkedlist","fn":"append","id":"69","ix":"7","pos":"558","caller":{"file":"node:internal/timers","fn":"listOnTimeout","id":"69","ix":"-1","pos":"14905","key":"listOnTimeout node:internal/timers"}},{"file":"node:internal/linkedlist","fn":"append","id":"80","ix":"2","pos":"558","caller":{"file":"node:timers","fn":"setInterval","id":"80","ix":"-1","pos":"5786","key":"setInterval node:timers"}},{"file":"node:internal/linkedlist","fn":"append","id":"83","ix":"6","pos":"558","caller":{"file":"node:internal/stream_base_commons","fn":"setStreamTimeout","id":"83","ix":"-1","pos":"6046","key":"setStreamTimeout node:internal/stream_base_commons"}}],"peek node:internal/linkedlist":[{"file":"node:internal/linkedlist","fn":"peek","id":"49","ix":"1","pos":"146","caller":{"file":"node:internal/timers","fn":"listOnTimeout","id":"49","ix":"-1","pos":"14905","key":"listOnTimeout node:internal/timers"}},{"file":"node:internal/linkedlist","fn":"peek","id":"69","ix":"1","pos":"146","caller":{"file":"node:internal/timers","fn":"listOnTimeout","id":"69","ix":"-1","pos":"14905","key":"listOnTimeout node:internal/timers"}}],"insert node:internal/timers":[{"file":"node:internal/timers","fn":"insert","id":"49","ix":"4","pos":"10384","caller":{"file":"node:internal/timers","fn":"listOnTimeout","id":"49","ix":"-1","pos":"14905","key":"listOnTimeout node:internal/timers"}},{"file":"node:internal/timers","fn":"insert","id":"61","ix":"4","pos":"10384","caller":{"file":"file:///mnt/d/Software/JS_Expert/modulo12/02-memory-leak/02-memleak-events/index.js","fn":"onData","id":"61","ix":"-1","pos":"210","key":"onData file:///mnt/d/Software/JS_Expert/modulo12/02-memory-leak/02-memleak-events/index.js"}},{"file":"node:internal/timers","fn":"insert","id":"69","ix":"6","pos":"10384","caller":{"file":"node:internal/timers","fn":"listOnTimeout","id":"69","ix":"-1","pos":"14905","key":"listOnTimeout node:internal/timers"}},{"file":"node:internal/timers","fn":"insert","id":"80","ix":"1","pos":"10384","caller":{"file":"node:timers","fn":"setInterval","id":"80","ix":"-1","pos":"5786","key":"setInterval node:timers"}},{"file":"node:internal/timers","fn":"insert","id":"83","ix":"5","pos":"10384","caller":{"file":"node:internal/stream_base_commons","fn":"setStreamTimeout","id":"83","ix":"-1","pos":"6046","key":"setStreamTimeout node:internal/stream_base_commons"}}],"myInterval file:///mnt/d/Software/JS_Expert/modulo12/02-memory-leak/02-memleak-events/index.js":[{"file":"file:///mnt/d/Software/JS_Expert/modulo12/02-memory-leak/02-memleak-events/index.js","fn":"myInterval","id":"49","ix":"5","pos":"282","caller":{"file":"node:internal/timers","fn":"listOnTimeout","id":"49","ix":"-1","pos":"14905","key":"listOnTimeout node:internal/timers"}}],"get node:_http_outgoing":[{"file":"node:_http_outgoing","fn":"get","id":"53","ix":"0","pos":"4943","caller":{"file":"node:_http_outgoing","fn":"end","id":"53","ix":"-1","pos":"24416","key":"end node:_http_outgoing"}}],"assertSize node:internal/crypto/random":[{"file":"node:internal/crypto/random","fn":"assertSize","id":"54","ix":"0","pos":"1499","caller":{"file":"node:internal/crypto/random","fn":"randomFillSync","id":"54","ix":"-1","pos":"2499","key":"randomFillSync node:internal/crypto/random"}},{"file":"node:internal/crypto/random","fn":"assertSize","id":"61","ix":"7","pos":"1499","caller":{"file":"file:///mnt/d/Software/JS_Expert/modulo12/02-memory-leak/02-memleak-events/index.js","fn":"onData","id":"61","ix":"-1","pos":"210","key":"onData file:///mnt/d/Software/JS_Expert/modulo12/02-memory-leak/02-memleak-events/index.js"}},{"file":"node:internal/crypto/random","fn":"assertSize","id":"79","ix":"2","pos":"1499","caller":{"file":"node:internal/crypto/random","fn":"randomBytes","id":"79","ix":"-1","pos":"1963","key":"randomBytes node:internal/crypto/random"}},{"file":"node:internal/crypto/random","fn":"assertSize","id":"79","ix":"2","pos":"1499","caller":{"file":"node:internal/crypto/random","fn":"randomBytes","id":"79","ix":"-1","pos":"1963","key":"randomBytes node:internal/crypto/random"}}],"assertOffset node:internal/crypto/random":[{"file":"node:internal/crypto/random","fn":"assertOffset","id":"54","ix":"1","pos":"1133","caller":{"file":"node:internal/crypto/random","fn":"randomFillSync","id":"54","ix":"-1","pos":"2499","key":"randomFillSync node:internal/crypto/random"}},{"file":"node:internal/crypto/random","fn":"assertOffset","id":"79","ix":"4","pos":"1133","caller":{"file":"node:internal/crypto/random","fn":"randomBytes","id":"79","ix":"-1","pos":"1963","key":"randomBytes node:internal/crypto/random"}}],"Readable.resume node:internal/streams/readable":[{"file":"node:internal/streams/readable","fn":"Readable.resume","id":"55","ix":"0","pos":"30769","caller":{"file":"node:net","fn":"Socket.resume","id":"55","ix":"-1","pos":"17240","key":"Socket.resume node:net"}}],"addListener node:events":[{"file":"node:events","fn":"addListener","id":"57","ix":"0","pos":"18237","caller":{"file":"node:internal/streams/readable","fn":"Readable.on","id":"57","ix":"-1","pos":"27748","key":"Readable.on node:internal/streams/readable"}}],"getBytes file:///mnt/d/Software/JS_Expert/modulo12/02-memory-leak/02-memleak-events/index.js":[{"file":"file:///mnt/d/Software/JS_Expert/modulo12/02-memory-leak/02-memleak-events/index.js","fn":"getBytes","id":"61","ix":"0","pos":"157","caller":{"file":"file:///mnt/d/Software/JS_Expert/modulo12/02-memory-leak/02-memleak-events/index.js","fn":"onData","id":"61","ix":"-1","pos":"210","key":"onData file:///mnt/d/Software/JS_Expert/modulo12/02-memory-leak/02-memleak-events/index.js"}},{"file":"file:///mnt/d/Software/JS_Expert/modulo12/02-memory-leak/02-memleak-events/index.js","fn":"getBytes","id":"82","ix":"0","pos":"157","caller":{"file":"file:///mnt/d/Software/JS_Expert/modulo12/02-memory-leak/02-memleak-events/index.js","fn":"onData","id":"82","ix":"-1","pos":"210","key":"onData file:///mnt/d/Software/JS_Expert/modulo12/02-memory-leak/02-memleak-events/index.js"}}],"setInterval node:timers":[{"file":"node:timers","fn":"setInterval","id":"61","ix":"1","pos":"5786","caller":{"file":"file:///mnt/d/Software/JS_Expert/modulo12/02-memory-leak/02-memleak-events/index.js","fn":"onData","id":"61","ix":"-1","pos":"210","key":"onData file:///mnt/d/Software/JS_Expert/modulo12/02-memory-leak/02-memleak-events/index.js"}}],"randomBytes node:internal/crypto/random":[{"file":"node:internal/crypto/random","fn":"randomBytes","id":"61","ix":"3","pos":"1963","caller":{"file":"file:///mnt/d/Software/JS_Expert/modulo12/02-memory-leak/02-memleak-events/index.js","fn":"onData","id":"61","ix":"-1","pos":"210","key":"onData file:///mnt/d/Software/JS_Expert/modulo12/02-memory-leak/02-memleak-events/index.js"}}],"FastBuffer node:internal/buffer":[{"file":"node:internal/buffer","fn":"FastBuffer","id":"61","ix":"6","pos":"26364","caller":{"file":"file:///mnt/d/Software/JS_Expert/modulo12/02-memory-leak/02-memleak-events/index.js","fn":"onData","id":"61","ix":"-1","pos":"210","key":"onData file:///mnt/d/Software/JS_Expert/modulo12/02-memory-leak/02-memleak-events/index.js"}},{"file":"node:internal/buffer","fn":"FastBuffer","id":"79","ix":"1","pos":"26364","caller":{"file":"node:internal/crypto/random","fn":"randomBytes","id":"79","ix":"-1","pos":"1963","key":"randomBytes node:internal/crypto/random"}}],"flow node:internal/streams/readable":[{"file":"node:internal/streams/readable","fn":"flow","id":"62","ix":"1","pos":"31804","caller":{"file":"node:internal/streams/readable","fn":"emitReadable_","id":"62","ix":"-1","pos":"18430","key":"emitReadable_ node:internal/streams/readable"}},{"file":"node:internal/streams/readable","fn":"flow","id":"68","ix":"1","pos":"31804","caller":{"file":"node:internal/streams/readable","fn":"resume_","id":"68","ix":"-1","pos":"31257","key":"resume_ node:internal/streams/readable"}}],"isUint8Array node:internal/util/types":[{"file":"node:internal/util/types","fn":"isUint8Array","id":"65","ix":"1","pos":"257","caller":{"file":"node:internal/streams/readable","fn":"readableAddChunk","id":"65","ix":"-1","pos":"7908","key":"readableAddChunk node:internal/streams/readable"}}],"onEofChunk node:internal/streams/readable":[{"file":"node:internal/streams/readable","fn":"onEofChunk","id":"65","ix":"2","pos":"17077","caller":{"file":"node:internal/streams/readable","fn":"readableAddChunk","id":"65","ix":"-1","pos":"7908","key":"readableAddChunk node:internal/streams/readable"}}],"emitReadable node:internal/streams/readable":[{"file":"node:internal/streams/readable","fn":"emitReadable","id":"65","ix":"3","pos":"18100","caller":{"file":"node:internal/streams/readable","fn":"readableAddChunk","id":"65","ix":"-1","pos":"7908","key":"readableAddChunk node:internal/streams/readable"}}],"onDestroy node:internal/streams/destroy":[{"file":"node:internal/streams/destroy","fn":"onDestroy","id":"72","ix":"0","pos":"1535","caller":{"file":"node:_http_incoming","fn":"onError","id":"72","ix":"-1","pos":"12652","key":"onError node:_http_incoming"}}],"listenerCount node:events":[{"file":"node:events","fn":"listenerCount","id":"72","ix":"1","pos":"24662","caller":{"file":"node:_http_incoming","fn":"onError","id":"72","ix":"-1","pos":"12652","key":"onError node:_http_incoming"}}],"insertGuarded node:internal/timers":[{"file":"node:internal/timers","fn":"insertGuarded","id":"74","ix":"2","pos":"9873","caller":{"file":"node:net","fn":"_unrefTimer","id":"74","ix":"-1","pos":"11830","key":"_unrefTimer node:net"}},{"file":"node:internal/timers","fn":"insertGuarded","id":"84","ix":"4","pos":"9873","caller":{"file":"node:_http_server","fn":"onParserExecute","id":"84","ix":"-1","pos":"21546","key":"onParserExecute node:_http_server"}}],"Readable.push node:internal/streams/readable":[{"file":"node:internal/streams/readable","fn":"Readable.push","id":"76","ix":"0","pos":"7621","caller":{"file":"node:_http_common","fn":"parserOnMessageComplete","id":"76","ix":"-1","pos":"4908","key":"parserOnMessageComplete node:_http_common"}}],"readStart node:_http_incoming":[{"file":"node:_http_incoming","fn":"readStart","id":"76","ix":"1","pos":"1557","caller":{"file":"node:_http_common","fn":"parserOnMessageComplete","id":"76","ix":"-1","pos":"4908","key":"parserOnMessageComplete node:_http_common"}}],"randomFillSync node:internal/crypto/random":[{"file":"node:internal/crypto/random","fn":"randomFillSync","id":"79","ix":"0","pos":"2499","caller":{"file":"node:internal/crypto/random","fn":"randomBytes","id":"79","ix":"-1","pos":"1963","key":"randomBytes node:internal/crypto/random"}}],"Timeout node:internal/timers":[{"file":"node:internal/timers","fn":"Timeout","id":"80","ix":"3","pos":"5778","caller":{"file":"node:timers","fn":"setInterval","id":"80","ix":"-1","pos":"5786","key":"setInterval node:timers"}}],"clearTimeout node:timers":[{"file":"node:timers","fn":"clearTimeout","id":"83","ix":"0","pos":"5184","caller":{"file":"node:internal/stream_base_commons","fn":"setStreamTimeout","id":"83","ix":"-1","pos":"6046","key":"setStreamTimeout node:internal/stream_base_commons"}}],"getTimerDuration node:internal/timers":[{"file":"node:internal/timers","fn":"getTimerDuration","id":"83","ix":"1","pos":"11360","caller":{"file":"node:internal/stream_base_commons","fn":"setStreamTimeout","id":"83","ix":"-1","pos":"6046","key":"setStreamTimeout node:internal/stream_base_commons"}}],"setUnrefTimeout node:internal/timers":[{"file":"node:internal/timers","fn":"setUnrefTimeout","id":"83","ix":"3","pos":"11046","caller":{"file":"node:internal/stream_base_commons","fn":"setStreamTimeout","id":"83","ix":"-1","pos":"6046","key":"setStreamTimeout node:internal/stream_base_commons"}}],"unenroll node:timers":[{"file":"node:timers","fn":"unenroll","id":"83","ix":"7","pos":"2349","caller":{"file":"node:internal/stream_base_commons","fn":"setStreamTimeout","id":"83","ix":"-1","pos":"6046","key":"setStreamTimeout node:internal/stream_base_commons"}}],"_write node:internal/streams/writable":[{"file":"node:internal/streams/writable","fn":"_write","id":"85","ix":"0","pos":"9383","caller":{"file":"node:internal/streams/writable","fn":"Writable.write","id":"85","ix":"-1","pos":"10749","key":"Writable.write node:internal/streams/writable"}}],"onwriteError node:internal/streams/writable":[{"file":"node:internal/streams/writable","fn":"onwriteError","id":"96","ix":"13","pos":"13062","caller":{"file":"node:internal/process/task_queues","fn":"processTicksAndRejections","id":"96","ix":"-1","pos":"1496","key":"processTicksAndRejections node:internal/process/task_queues"}}],"errorOrDestroy node:internal/streams/destroy":[{"file":"node:internal/streams/destroy","fn":"errorOrDestroy","id":"96","ix":"14","pos":"3686","caller":{"file":"node:internal/process/task_queues","fn":"processTicksAndRejections","id":"96","ix":"-1","pos":"1496","key":"processTicksAndRejections node:internal/process/task_queues"}}]}}